<?xml version="1.0"?>
<pecan>
 <state.data.assimilation>
  <process.variance>TRUE</process.variance>
  <adjustment>FALSE</adjustment>
  <censored.data>FALSE</censored.data>
  <q.type>SINGLE</q.type>
  <Localization.FUN>Local.support</Localization.FUN>
  <scalef>1</scalef>
  <data>
   <format_id>1000000040</format_id>
   <input.id>1000013298</input.id>
  </data>
  <state.variables>
   <variable>
    <variable.name>AbvGrndWood</variable.name>
    <unit>MgC/ha</unit>
    <min_value>0</min_value>
    <max_value>9999</max_value>
   </variable>
   <variable>
    <variable.name>LAI</variable.name>
    <unit></unit>
    <min_value>0</min_value>
    <max_value>9999</max_value>
   </variable>
   <variable>
    <variable.name>TotSoilCarb</variable.name>
    <unit>kg/m^2</unit>
    <min_value>0</min_value>
    <max_value>9999</max_value>
   </variable>
  </state.variables>
  <forecast.time.step>year</forecast.time.step>
  <start.date>2012/01/01</start.date>
  <end.date>2021/12/31</end.date>
 </state.data.assimilation>
 <info>
  <notes></notes>
  <userid>-1</userid>
  <username></username>
  <date>2017/12/06 21:19:33 +0000</date>
 </info>
 <outdir>/projectnb/dietzelab/dongchen/All_NEON_SDA/NEON42/SDA</outdir>
 <rundir>/projectnb/dietzelab/dongchen/All_NEON_SDA/NEON42/SDA/run</rundir>
 <modeloutdir>/projectnb/dietzelab/dongchen/All_NEON_SDA/NEON42/SDA/out</modeloutdir>
 <database>
  <bety>
   <user>bety</user>
   <password>bety</password>
   <host>128.197.168.114</host>
   <dbname>bety</dbname>
   <driver>PostgreSQL</driver>
   <write>FALSE</write>
  </bety>
 </database>
 <pfts>
  <pft>
   <name>temperate.deciduous.HPDA</name>
   <constants>
    <num>1</num>
   </constants>
   <posteriorid>1000022311</posteriorid>
   <outdir>/fs/data2/output//PEcAn_1000010530/pft/temperate.deciduous.HPDA</outdir>
  </pft>
  <pft>
   <name>boreal.coniferous</name>
   <outdir>/projectnb/dietzelab/hamzed/SDA/ProductionRun/50Sites/SDA_50Sites_1000008768/pft/Conifer/boreal.coniferous</outdir>
  </pft>
  <pft>
   <name>semiarid.grassland_HPDA</name>
   <constants>
    <num>1</num>
   </constants>
   <posteriorid>1000016525</posteriorid>
   <outdir>/projectnb/dietzelab/hamzed/SDA/ProductionRun/50Sites/SDA_50Sites_1000008768/pft/GrassA/semiarid.grassland</outdir>
  </pft>
 </pfts>
 <meta.analysis>
  <iter>3000</iter>
  <random.effects>FALSE</random.effects>
 </meta.analysis>
 <ensemble>
  <size>25</size>
  <variable>NPP</variable>
  <samplingspace>
   <parameters>
    <method>uniform</method>
   </parameters>
   <met>
    <method>sampling</method>
   </met>
  </samplingspace>
 </ensemble>
 <model>
  <id>1000000022</id>
  <type>SIPNET</type>
  <revision>ssr</revision>
  <delete.raw>FALSE</delete.raw>
  <binary>/usr2/postdoc/istfer/SIPNET/trunk//sipnet_if</binary>
  <jobtemplate>~/sipnet_geo.job</jobtemplate>
 </model>
 <host>
  <name>geo.bu.edu</name>
  <usr>zhangdc</usr>
  <folder>/projectnb/dietzelab/dongchen/All_NEON_SDA/NEON42/SDA/out</folder>
  <prerun>module load R/4.0.5</prerun>
  <qsub>qsub -l h_rt=24:00:00 -q &apos;geo*&apos; -N @NAME@ -o @STDOUT@ -e @STDERR@ -S /bin/bash</qsub>
  <qsub.jobid>Your job ([0-9]+) .*</qsub.jobid>
  <qstat>qstat -j @JOBID@ || echo DONE</qstat>
  <tunnel>~/Tunnel/Tunnel</tunnel>
  <outdir>/projectnb/dietzelab/dongchen/All_NEON_SDA/NEON42/SDA/out</outdir>
  <rundir>/projectnb/dietzelab/dongchen/All_NEON_SDA/NEON42/SDA/run</rundir>
 </host>
 <settings.info>
  <deprecated.settings.fixed>TRUE</deprecated.settings.fixed>
  <settings.updated>TRUE</settings.updated>
  <checked>TRUE</checked>
 </settings.info>
 <run>
  <settings.1>
   <site>
    <id>1000004920</id>
    <met.start>2012/01/01</met.start>
    <met.end>2021/12/31</met.end>
    <lat>39.06026</lat>
    <lon>-78.07164</lon>
    <name>1000004920</name>
   </site>
   <start.date>2012/01/01</start.date>
   <end.date>2021/12/31</end.date>
   <inputs>
    <met>
     <source>ERA5</source>
     <output>SIPNET</output>
     <id></id>
     <path>
      <path>/projectnb/dietzelab/dongchen/All_NEON_SDA/NEON42/ERA5_2012_2021/1000004920/ERA5.1.2012-01-01.2021-12-31.clim</path>
      <path>/projectnb/dietzelab/dongchen/All_NEON_SDA/NEON42/ERA5_2012_2021/1000004920/ERA5.10.2012-01-01.2021-12-31.clim</path>
      <path>/projectnb/dietzelab/dongchen/All_NEON_SDA/NEON42/ERA5_2012_2021/1000004920/ERA5.2.2012-01-01.2021-12-31.clim</path>
      <path>/projectnb/dietzelab/dongchen/All_NEON_SDA/NEON42/ERA5_2012_2021/1000004920/ERA5.3.2012-01-01.2021-12-31.clim</path>
      <path>/projectnb/dietzelab/dongchen/All_NEON_SDA/NEON42/ERA5_2012_2021/1000004920/ERA5.4.2012-01-01.2021-12-31.clim</path>
      <path>/projectnb/dietzelab/dongchen/All_NEON_SDA/NEON42/ERA5_2012_2021/1000004920/ERA5.5.2012-01-01.2021-12-31.clim</path>
      <path>/projectnb/dietzelab/dongchen/All_NEON_SDA/NEON42/ERA5_2012_2021/1000004920/ERA5.6.2012-01-01.2021-12-31.clim</path>
      <path>/projectnb/dietzelab/dongchen/All_NEON_SDA/NEON42/ERA5_2012_2021/1000004920/ERA5.7.2012-01-01.2021-12-31.clim</path>
      <path>/projectnb/dietzelab/dongchen/All_NEON_SDA/NEON42/ERA5_2012_2021/1000004920/ERA5.8.2012-01-01.2021-12-31.clim</path>
      <path>/projectnb/dietzelab/dongchen/All_NEON_SDA/NEON42/ERA5_2012_2021/1000004920/ERA5.9.2012-01-01.2021-12-31.clim</path>
     </path>
    </met>
    <pft.site>
     <path>/projectnb/dietzelab/dongchen/All_NEON_SDA/NEON42/site_pft.csv</path>
    </pft.site>
   </inputs>
  </settings.1>
  <settings.2>
   <site>
    <id>1000004875</id>
    <met.start>2012/01/01</met.start>
    <met.end>2021/12/31</met.end>
    <lat>40.17759</lat>
    <lon>-112.45244</lon>
    <name>1000004875</name>
   </site>
   <start.date>2012/01/01</start.date>
   <end.date>2021/12/31</end.date>
   <inputs>
    <met>
     <source>ERA5</source>
     <output>SIPNET</output>
     <id></id>
     <path>
      <path>/projectnb/dietzelab/dongchen/All_NEON_SDA/NEON42/ERA5_2012_2021/1000004875/ERA5.1.2012-01-01.2021-12-31.clim</path>
      <path>/projectnb/dietzelab/dongchen/All_NEON_SDA/NEON42/ERA5_2012_2021/1000004875/ERA5.10.2012-01-01.2021-12-31.clim</path>
      <path>/projectnb/dietzelab/dongchen/All_NEON_SDA/NEON42/ERA5_2012_2021/1000004875/ERA5.2.2012-01-01.2021-12-31.clim</path>
      <path>/projectnb/dietzelab/dongchen/All_NEON_SDA/NEON42/ERA5_2012_2021/1000004875/ERA5.3.2012-01-01.2021-12-31.clim</path>
      <path>/projectnb/dietzelab/dongchen/All_NEON_SDA/NEON42/ERA5_2012_2021/1000004875/ERA5.4.2012-01-01.2021-12-31.clim</path>
      <path>/projectnb/dietzelab/dongchen/All_NEON_SDA/NEON42/ERA5_2012_2021/1000004875/ERA5.5.2012-01-01.2021-12-31.clim</path>
      <path>/projectnb/dietzelab/dongchen/All_NEON_SDA/NEON42/ERA5_2012_2021/1000004875/ERA5.6.2012-01-01.2021-12-31.clim</path>
      <path>/projectnb/dietzelab/dongchen/All_NEON_SDA/NEON42/ERA5_2012_2021/1000004875/ERA5.7.2012-01-01.2021-12-31.clim</path>
      <path>/projectnb/dietzelab/dongchen/All_NEON_SDA/NEON42/ERA5_2012_2021/1000004875/ERA5.8.2012-01-01.2021-12-31.clim</path>
      <path>/projectnb/dietzelab/dongchen/All_NEON_SDA/NEON42/ERA5_2012_2021/1000004875/ERA5.9.2012-01-01.2021-12-31.clim</path>
     </path>
    </met>
    <pft.site>
     <path>/projectnb/dietzelab/dongchen/All_NEON_SDA/NEON42/site_pft.csv</path>
    </pft.site>
   </inputs>
  </settings.2>
  <settings.3>
   <site>
    <id>1000004931</id>
    <met.start>2012/01/01</met.start>
    <met.end>2021/12/31</met.end>
    <lat>46.76972</lat>
    <lon>-100.91535</lon>
    <name>1000004931</name>
   </site>
   <start.date>2012/01/01</start.date>
   <end.date>2021/12/31</end.date>
   <inputs>
    <met>
     <source>ERA5</source>
     <output>SIPNET</output>
     <id></id>
     <path>
      <path>/projectnb/dietzelab/dongchen/All_NEON_SDA/NEON42/ERA5_2012_2021/1000004931/ERA5.1.2012-01-01.2021-12-31.clim</path>
      <path>/projectnb/dietzelab/dongchen/All_NEON_SDA/NEON42/ERA5_2012_2021/1000004931/ERA5.10.2012-01-01.2021-12-31.clim</path>
      <path>/projectnb/dietzelab/dongchen/All_NEON_SDA/NEON42/ERA5_2012_2021/1000004931/ERA5.2.2012-01-01.2021-12-31.clim</path>
      <path>/projectnb/dietzelab/dongchen/All_NEON_SDA/NEON42/ERA5_2012_2021/1000004931/ERA5.3.2012-01-01.2021-12-31.clim</path>
      <path>/projectnb/dietzelab/dongchen/All_NEON_SDA/NEON42/ERA5_2012_2021/1000004931/ERA5.4.2012-01-01.2021-12-31.clim</path>
      <path>/projectnb/dietzelab/dongchen/All_NEON_SDA/NEON42/ERA5_2012_2021/1000004931/ERA5.5.2012-01-01.2021-12-31.clim</path>
      <path>/projectnb/dietzelab/dongchen/All_NEON_SDA/NEON42/ERA5_2012_2021/1000004931/ERA5.6.2012-01-01.2021-12-31.clim</path>
      <path>/projectnb/dietzelab/dongchen/All_NEON_SDA/NEON42/ERA5_2012_2021/1000004931/ERA5.7.2012-01-01.2021-12-31.clim</path>
      <path>/projectnb/dietzelab/dongchen/All_NEON_SDA/NEON42/ERA5_2012_2021/1000004931/ERA5.8.2012-01-01.2021-12-31.clim</path>
      <path>/projectnb/dietzelab/dongchen/All_NEON_SDA/NEON42/ERA5_2012_2021/1000004931/ERA5.9.2012-01-01.2021-12-31.clim</path>
     </path>
    </met>
    <pft.site>
     <path>/projectnb/dietzelab/dongchen/All_NEON_SDA/NEON42/site_pft.csv</path>
    </pft.site>
   </inputs>
  </settings.3>
  <settings.4>
   <site>
    <id>1000004891</id>
    <met.start>2012/01/01</met.start>
    <met.end>2021/12/31</met.end>
    <lat>37.00583</lat>
    <lon>-119.00602</lon>
    <name>1000004891</name>
   </site>
   <start.date>2012/01/01</start.date>
   <end.date>2021/12/31</end.date>
   <inputs>
    <met>
     <source>ERA5</source>
     <output>SIPNET</output>
     <id></id>
     <path>
      <path>/projectnb/dietzelab/dongchen/All_NEON_SDA/NEON42/ERA5_2012_2021/1000004891/ERA5.1.2012-01-01.2021-12-31.clim</path>
      <path>/projectnb/dietzelab/dongchen/All_NEON_SDA/NEON42/ERA5_2012_2021/1000004891/ERA5.10.2012-01-01.2021-12-31.clim</path>
      <path>/projectnb/dietzelab/dongchen/All_NEON_SDA/NEON42/ERA5_2012_2021/1000004891/ERA5.2.2012-01-01.2021-12-31.clim</path>
      <path>/projectnb/dietzelab/dongchen/All_NEON_SDA/NEON42/ERA5_2012_2021/1000004891/ERA5.3.2012-01-01.2021-12-31.clim</path>
      <path>/projectnb/dietzelab/dongchen/All_NEON_SDA/NEON42/ERA5_2012_2021/1000004891/ERA5.4.2012-01-01.2021-12-31.clim</path>
      <path>/projectnb/dietzelab/dongchen/All_NEON_SDA/NEON42/ERA5_2012_2021/1000004891/ERA5.5.2012-01-01.2021-12-31.clim</path>
      <path>/projectnb/dietzelab/dongchen/All_NEON_SDA/NEON42/ERA5_2012_2021/1000004891/ERA5.6.2012-01-01.2021-12-31.clim</path>
      <path>/projectnb/dietzelab/dongchen/All_NEON_SDA/NEON42/ERA5_2012_2021/1000004891/ERA5.7.2012-01-01.2021-12-31.clim</path>
      <path>/projectnb/dietzelab/dongchen/All_NEON_SDA/NEON42/ERA5_2012_2021/1000004891/ERA5.8.2012-01-01.2021-12-31.clim</path>
      <path>/projectnb/dietzelab/dongchen/All_NEON_SDA/NEON42/ERA5_2012_2021/1000004891/ERA5.9.2012-01-01.2021-12-31.clim</path>
     </path>
    </met>
    <pft.site>
     <path>/projectnb/dietzelab/dongchen/All_NEON_SDA/NEON42/site_pft.csv</path>
    </pft.site>
   </inputs>
  </settings.4>
  <settings.5>
   <site>
    <id>1000004937</id>
    <met.start>2012/01/01</met.start>
    <met.end>2021/12/31</met.end>
    <lat>32.54172</lat>
    <lon>-87.80389</lon>
    <name>1000004937</name>
   </site>
   <start.date>2012/01/01</start.date>
   <end.date>2021/12/31</end.date>
   <inputs>
    <met>
     <source>ERA5</source>
     <output>SIPNET</output>
     <id></id>
     <path>
      <path>/projectnb/dietzelab/dongchen/All_NEON_SDA/NEON42/ERA5_2012_2021/1000004937/ERA5.1.2012-01-01.2021-12-31.clim</path>
      <path>/projectnb/dietzelab/dongchen/All_NEON_SDA/NEON42/ERA5_2012_2021/1000004937/ERA5.10.2012-01-01.2021-12-31.clim</path>
      <path>/projectnb/dietzelab/dongchen/All_NEON_SDA/NEON42/ERA5_2012_2021/1000004937/ERA5.2.2012-01-01.2021-12-31.clim</path>
      <path>/projectnb/dietzelab/dongchen/All_NEON_SDA/NEON42/ERA5_2012_2021/1000004937/ERA5.3.2012-01-01.2021-12-31.clim</path>
      <path>/projectnb/dietzelab/dongchen/All_NEON_SDA/NEON42/ERA5_2012_2021/1000004937/ERA5.4.2012-01-01.2021-12-31.clim</path>
      <path>/projectnb/dietzelab/dongchen/All_NEON_SDA/NEON42/ERA5_2012_2021/1000004937/ERA5.5.2012-01-01.2021-12-31.clim</path>
      <path>/projectnb/dietzelab/dongchen/All_NEON_SDA/NEON42/ERA5_2012_2021/1000004937/ERA5.6.2012-01-01.2021-12-31.clim</path>
      <path>/projectnb/dietzelab/dongchen/All_NEON_SDA/NEON42/ERA5_2012_2021/1000004937/ERA5.7.2012-01-01.2021-12-31.clim</path>
      <path>/projectnb/dietzelab/dongchen/All_NEON_SDA/NEON42/ERA5_2012_2021/1000004937/ERA5.8.2012-01-01.2021-12-31.clim</path>
      <path>/projectnb/dietzelab/dongchen/All_NEON_SDA/NEON42/ERA5_2012_2021/1000004937/ERA5.9.2012-01-01.2021-12-31.clim</path>
     </path>
    </met>
    <pft.site>
     <path>/projectnb/dietzelab/dongchen/All_NEON_SDA/NEON42/site_pft.csv</path>
    </pft.site>
   </inputs>
  </settings.5>
  <settings.6>
   <site>
    <id>1000004911</id>
    <met.start>2012/01/01</met.start>
    <met.end>2021/12/31</met.end>
    <lat>45.50894</lat>
    <lon>-89.58637</lon>
    <name>1000004911</name>
   </site>
   <start.date>2012/01/01</start.date>
   <end.date>2021/12/31</end.date>
   <inputs>
    <met>
     <source>ERA5</source>
     <output>SIPNET</output>
     <id></id>
     <path>
      <path>/projectnb/dietzelab/dongchen/All_NEON_SDA/NEON42/ERA5_2012_2021/1000004911/ERA5.1.2012-01-01.2021-12-31.clim</path>
      <path>/projectnb/dietzelab/dongchen/All_NEON_SDA/NEON42/ERA5_2012_2021/1000004911/ERA5.10.2012-01-01.2021-12-31.clim</path>
      <path>/projectnb/dietzelab/dongchen/All_NEON_SDA/NEON42/ERA5_2012_2021/1000004911/ERA5.2.2012-01-01.2021-12-31.clim</path>
      <path>/projectnb/dietzelab/dongchen/All_NEON_SDA/NEON42/ERA5_2012_2021/1000004911/ERA5.3.2012-01-01.2021-12-31.clim</path>
      <path>/projectnb/dietzelab/dongchen/All_NEON_SDA/NEON42/ERA5_2012_2021/1000004911/ERA5.4.2012-01-01.2021-12-31.clim</path>
      <path>/projectnb/dietzelab/dongchen/All_NEON_SDA/NEON42/ERA5_2012_2021/1000004911/ERA5.5.2012-01-01.2021-12-31.clim</path>
      <path>/projectnb/dietzelab/dongchen/All_NEON_SDA/NEON42/ERA5_2012_2021/1000004911/ERA5.6.2012-01-01.2021-12-31.clim</path>
      <path>/projectnb/dietzelab/dongchen/All_NEON_SDA/NEON42/ERA5_2012_2021/1000004911/ERA5.7.2012-01-01.2021-12-31.clim</path>
      <path>/projectnb/dietzelab/dongchen/All_NEON_SDA/NEON42/ERA5_2012_2021/1000004911/ERA5.8.2012-01-01.2021-12-31.clim</path>
      <path>/projectnb/dietzelab/dongchen/All_NEON_SDA/NEON42/ERA5_2012_2021/1000004911/ERA5.9.2012-01-01.2021-12-31.clim</path>
     </path>
    </met>
    <pft.site>
     <path>/projectnb/dietzelab/dongchen/All_NEON_SDA/NEON42/site_pft.csv</path>
    </pft.site>
   </inputs>
  </settings.6>
  <settings.7>
   <site>
    <id>1000004927</id>
    <met.start>2012/01/01</met.start>
    <met.end>2021/12/31</met.end>
    <lat>39.10077</lat>
    <lon>-96.56309</lon>
    <name>1000004927</name>
   </site>
   <start.date>2012/01/01</start.date>
   <end.date>2021/12/31</end.date>
   <inputs>
    <met>
     <source>ERA5</source>
     <output>SIPNET</output>
     <id></id>
     <path>
      <path>/projectnb/dietzelab/dongchen/All_NEON_SDA/NEON42/ERA5_2012_2021/1000004927/ERA5.1.2012-01-01.2021-12-31.clim</path>
      <path>/projectnb/dietzelab/dongchen/All_NEON_SDA/NEON42/ERA5_2012_2021/1000004927/ERA5.10.2012-01-01.2021-12-31.clim</path>
      <path>/projectnb/dietzelab/dongchen/All_NEON_SDA/NEON42/ERA5_2012_2021/1000004927/ERA5.2.2012-01-01.2021-12-31.clim</path>
      <path>/projectnb/dietzelab/dongchen/All_NEON_SDA/NEON42/ERA5_2012_2021/1000004927/ERA5.3.2012-01-01.2021-12-31.clim</path>
      <path>/projectnb/dietzelab/dongchen/All_NEON_SDA/NEON42/ERA5_2012_2021/1000004927/ERA5.4.2012-01-01.2021-12-31.clim</path>
      <path>/projectnb/dietzelab/dongchen/All_NEON_SDA/NEON42/ERA5_2012_2021/1000004927/ERA5.5.2012-01-01.2021-12-31.clim</path>
      <path>/projectnb/dietzelab/dongchen/All_NEON_SDA/NEON42/ERA5_2012_2021/1000004927/ERA5.6.2012-01-01.2021-12-31.clim</path>
      <path>/projectnb/dietzelab/dongchen/All_NEON_SDA/NEON42/ERA5_2012_2021/1000004927/ERA5.7.2012-01-01.2021-12-31.clim</path>
      <path>/projectnb/dietzelab/dongchen/All_NEON_SDA/NEON42/ERA5_2012_2021/1000004927/ERA5.8.2012-01-01.2021-12-31.clim</path>
      <path>/projectnb/dietzelab/dongchen/All_NEON_SDA/NEON42/ERA5_2012_2021/1000004927/ERA5.9.2012-01-01.2021-12-31.clim</path>
     </path>
    </met>
    <pft.site>
     <path>/projectnb/dietzelab/dongchen/All_NEON_SDA/NEON42/site_pft.csv</path>
    </pft.site>
   </inputs>
  </settings.7>
  <settings.8>
   <site>
    <id>1000004909</id>
    <met.start>2012/01/01</met.start>
    <met.end>2021/12/31</met.end>
    <lat>46.23388</lat>
    <lon>-89.53725</lon>
    <name>1000004909</name>
   </site>
   <start.date>2012/01/01</start.date>
   <end.date>2021/12/31</end.date>
   <inputs>
    <met>
     <source>ERA5</source>
     <output>SIPNET</output>
     <id></id>
     <path>
      <path>/projectnb/dietzelab/dongchen/All_NEON_SDA/NEON42/ERA5_2012_2021/1000004909/ERA5.1.2012-01-01.2021-12-31.clim</path>
      <path>/projectnb/dietzelab/dongchen/All_NEON_SDA/NEON42/ERA5_2012_2021/1000004909/ERA5.10.2012-01-01.2021-12-31.clim</path>
      <path>/projectnb/dietzelab/dongchen/All_NEON_SDA/NEON42/ERA5_2012_2021/1000004909/ERA5.2.2012-01-01.2021-12-31.clim</path>
      <path>/projectnb/dietzelab/dongchen/All_NEON_SDA/NEON42/ERA5_2012_2021/1000004909/ERA5.3.2012-01-01.2021-12-31.clim</path>
      <path>/projectnb/dietzelab/dongchen/All_NEON_SDA/NEON42/ERA5_2012_2021/1000004909/ERA5.4.2012-01-01.2021-12-31.clim</path>
      <path>/projectnb/dietzelab/dongchen/All_NEON_SDA/NEON42/ERA5_2012_2021/1000004909/ERA5.5.2012-01-01.2021-12-31.clim</path>
      <path>/projectnb/dietzelab/dongchen/All_NEON_SDA/NEON42/ERA5_2012_2021/1000004909/ERA5.6.2012-01-01.2021-12-31.clim</path>
      <path>/projectnb/dietzelab/dongchen/All_NEON_SDA/NEON42/ERA5_2012_2021/1000004909/ERA5.7.2012-01-01.2021-12-31.clim</path>
      <path>/projectnb/dietzelab/dongchen/All_NEON_SDA/NEON42/ERA5_2012_2021/1000004909/ERA5.8.2012-01-01.2021-12-31.clim</path>
      <path>/projectnb/dietzelab/dongchen/All_NEON_SDA/NEON42/ERA5_2012_2021/1000004909/ERA5.9.2012-01-01.2021-12-31.clim</path>
     </path>
    </met>
    <pft.site>
     <path>/projectnb/dietzelab/dongchen/All_NEON_SDA/NEON42/site_pft.csv</path>
    </pft.site>
   </inputs>
  </settings.8>
  <settings.9>
   <site>
    <id>1000004908</id>
    <met.start>2012/01/01</met.start>
    <met.end>2021/12/31</met.end>
    <lat>45.49369</lat>
    <lon>-89.58571</lon>
    <name>1000004908</name>
   </site>
   <start.date>2012/01/01</start.date>
   <end.date>2021/12/31</end.date>
   <inputs>
    <met>
     <source>ERA5</source>
     <output>SIPNET</output>
     <id></id>
     <path>
      <path>/projectnb/dietzelab/dongchen/All_NEON_SDA/NEON42/ERA5_2012_2021/1000004908/ERA5.1.2012-01-01.2021-12-31.clim</path>
      <path>/projectnb/dietzelab/dongchen/All_NEON_SDA/NEON42/ERA5_2012_2021/1000004908/ERA5.10.2012-01-01.2021-12-31.clim</path>
      <path>/projectnb/dietzelab/dongchen/All_NEON_SDA/NEON42/ERA5_2012_2021/1000004908/ERA5.2.2012-01-01.2021-12-31.clim</path>
      <path>/projectnb/dietzelab/dongchen/All_NEON_SDA/NEON42/ERA5_2012_2021/1000004908/ERA5.3.2012-01-01.2021-12-31.clim</path>
      <path>/projectnb/dietzelab/dongchen/All_NEON_SDA/NEON42/ERA5_2012_2021/1000004908/ERA5.4.2012-01-01.2021-12-31.clim</path>
      <path>/projectnb/dietzelab/dongchen/All_NEON_SDA/NEON42/ERA5_2012_2021/1000004908/ERA5.5.2012-01-01.2021-12-31.clim</path>
      <path>/projectnb/dietzelab/dongchen/All_NEON_SDA/NEON42/ERA5_2012_2021/1000004908/ERA5.6.2012-01-01.2021-12-31.clim</path>
      <path>/projectnb/dietzelab/dongchen/All_NEON_SDA/NEON42/ERA5_2012_2021/1000004908/ERA5.7.2012-01-01.2021-12-31.clim</path>
      <path>/projectnb/dietzelab/dongchen/All_NEON_SDA/NEON42/ERA5_2012_2021/1000004908/ERA5.8.2012-01-01.2021-12-31.clim</path>
      <path>/projectnb/dietzelab/dongchen/All_NEON_SDA/NEON42/ERA5_2012_2021/1000004908/ERA5.9.2012-01-01.2021-12-31.clim</path>
     </path>
    </met>
    <pft.site>
     <path>/projectnb/dietzelab/dongchen/All_NEON_SDA/NEON42/site_pft.csv</path>
    </pft.site>
   </inputs>
  </settings.9>
  <settings.10>
   <site>
    <id>1000004921</id>
    <met.start>2012/01/01</met.start>
    <met.end>2021/12/31</met.end>
    <lat>38.89008</lat>
    <lon>-76.56001</lon>
    <name>1000004921</name>
   </site>
   <start.date>2012/01/01</start.date>
   <end.date>2021/12/31</end.date>
   <inputs>
    <met>
     <source>ERA5</source>
     <output>SIPNET</output>
     <id></id>
     <path>
      <path>/projectnb/dietzelab/dongchen/All_NEON_SDA/NEON42/ERA5_2012_2021/1000004921/ERA5.1.2012-01-01.2021-12-31.clim</path>
      <path>/projectnb/dietzelab/dongchen/All_NEON_SDA/NEON42/ERA5_2012_2021/1000004921/ERA5.10.2012-01-01.2021-12-31.clim</path>
      <path>/projectnb/dietzelab/dongchen/All_NEON_SDA/NEON42/ERA5_2012_2021/1000004921/ERA5.2.2012-01-01.2021-12-31.clim</path>
      <path>/projectnb/dietzelab/dongchen/All_NEON_SDA/NEON42/ERA5_2012_2021/1000004921/ERA5.3.2012-01-01.2021-12-31.clim</path>
      <path>/projectnb/dietzelab/dongchen/All_NEON_SDA/NEON42/ERA5_2012_2021/1000004921/ERA5.4.2012-01-01.2021-12-31.clim</path>
      <path>/projectnb/dietzelab/dongchen/All_NEON_SDA/NEON42/ERA5_2012_2021/1000004921/ERA5.5.2012-01-01.2021-12-31.clim</path>
      <path>/projectnb/dietzelab/dongchen/All_NEON_SDA/NEON42/ERA5_2012_2021/1000004921/ERA5.6.2012-01-01.2021-12-31.clim</path>
      <path>/projectnb/dietzelab/dongchen/All_NEON_SDA/NEON42/ERA5_2012_2021/1000004921/ERA5.7.2012-01-01.2021-12-31.clim</path>
      <path>/projectnb/dietzelab/dongchen/All_NEON_SDA/NEON42/ERA5_2012_2021/1000004921/ERA5.8.2012-01-01.2021-12-31.clim</path>
      <path>/projectnb/dietzelab/dongchen/All_NEON_SDA/NEON42/ERA5_2012_2021/1000004921/ERA5.9.2012-01-01.2021-12-31.clim</path>
     </path>
    </met>
    <pft.site>
     <path>/projectnb/dietzelab/dongchen/All_NEON_SDA/NEON42/site_pft.csv</path>
    </pft.site>
   </inputs>
  </settings.10>
  <settings.11>
   <site>
    <id>1000004944</id>
    <met.start>2012/01/01</met.start>
    <met.end>2021/12/31</met.end>
    <lat>39.04043</lat>
    <lon>-95.19215</lon>
    <name>1000004944</name>
   </site>
   <start.date>2012/01/01</start.date>
   <end.date>2021/12/31</end.date>
   <inputs>
    <met>
     <source>ERA5</source>
     <output>SIPNET</output>
     <id></id>
     <path>
      <path>/projectnb/dietzelab/dongchen/All_NEON_SDA/NEON42/ERA5_2012_2021/1000004944/ERA5.1.2012-01-01.2021-12-31.clim</path>
      <path>/projectnb/dietzelab/dongchen/All_NEON_SDA/NEON42/ERA5_2012_2021/1000004944/ERA5.10.2012-01-01.2021-12-31.clim</path>
      <path>/projectnb/dietzelab/dongchen/All_NEON_SDA/NEON42/ERA5_2012_2021/1000004944/ERA5.2.2012-01-01.2021-12-31.clim</path>
      <path>/projectnb/dietzelab/dongchen/All_NEON_SDA/NEON42/ERA5_2012_2021/1000004944/ERA5.3.2012-01-01.2021-12-31.clim</path>
      <path>/projectnb/dietzelab/dongchen/All_NEON_SDA/NEON42/ERA5_2012_2021/1000004944/ERA5.4.2012-01-01.2021-12-31.clim</path>
      <path>/projectnb/dietzelab/dongchen/All_NEON_SDA/NEON42/ERA5_2012_2021/1000004944/ERA5.5.2012-01-01.2021-12-31.clim</path>
      <path>/projectnb/dietzelab/dongchen/All_NEON_SDA/NEON42/ERA5_2012_2021/1000004944/ERA5.6.2012-01-01.2021-12-31.clim</path>
      <path>/projectnb/dietzelab/dongchen/All_NEON_SDA/NEON42/ERA5_2012_2021/1000004944/ERA5.7.2012-01-01.2021-12-31.clim</path>
      <path>/projectnb/dietzelab/dongchen/All_NEON_SDA/NEON42/ERA5_2012_2021/1000004944/ERA5.8.2012-01-01.2021-12-31.clim</path>
      <path>/projectnb/dietzelab/dongchen/All_NEON_SDA/NEON42/ERA5_2012_2021/1000004944/ERA5.9.2012-01-01.2021-12-31.clim</path>
     </path>
    </met>
    <pft.site>
     <path>/projectnb/dietzelab/dongchen/All_NEON_SDA/NEON42/site_pft.csv</path>
    </pft.site>
   </inputs>
  </settings.11>
  <settings.12>
   <site>
    <id>1000004904</id>
    <met.start>2012/01/01</met.start>
    <met.end>2021/12/31</met.end>
    <lat>35.41059</lat>
    <lon>-99.05879</lon>
    <name>1000004904</name>
   </site>
   <start.date>2012/01/01</start.date>
   <end.date>2021/12/31</end.date>
   <inputs>
    <met>
     <source>ERA5</source>
     <output>SIPNET</output>
     <id></id>
     <path>
      <path>/projectnb/dietzelab/dongchen/All_NEON_SDA/NEON42/ERA5_2012_2021/1000004904/ERA5.1.2012-01-01.2021-12-31.clim</path>
      <path>/projectnb/dietzelab/dongchen/All_NEON_SDA/NEON42/ERA5_2012_2021/1000004904/ERA5.10.2012-01-01.2021-12-31.clim</path>
      <path>/projectnb/dietzelab/dongchen/All_NEON_SDA/NEON42/ERA5_2012_2021/1000004904/ERA5.2.2012-01-01.2021-12-31.clim</path>
      <path>/projectnb/dietzelab/dongchen/All_NEON_SDA/NEON42/ERA5_2012_2021/1000004904/ERA5.3.2012-01-01.2021-12-31.clim</path>
      <path>/projectnb/dietzelab/dongchen/All_NEON_SDA/NEON42/ERA5_2012_2021/1000004904/ERA5.4.2012-01-01.2021-12-31.clim</path>
      <path>/projectnb/dietzelab/dongchen/All_NEON_SDA/NEON42/ERA5_2012_2021/1000004904/ERA5.5.2012-01-01.2021-12-31.clim</path>
      <path>/projectnb/dietzelab/dongchen/All_NEON_SDA/NEON42/ERA5_2012_2021/1000004904/ERA5.6.2012-01-01.2021-12-31.clim</path>
      <path>/projectnb/dietzelab/dongchen/All_NEON_SDA/NEON42/ERA5_2012_2021/1000004904/ERA5.7.2012-01-01.2021-12-31.clim</path>
      <path>/projectnb/dietzelab/dongchen/All_NEON_SDA/NEON42/ERA5_2012_2021/1000004904/ERA5.8.2012-01-01.2021-12-31.clim</path>
      <path>/projectnb/dietzelab/dongchen/All_NEON_SDA/NEON42/ERA5_2012_2021/1000004904/ERA5.9.2012-01-01.2021-12-31.clim</path>
     </path>
    </met>
    <pft.site>
     <path>/projectnb/dietzelab/dongchen/All_NEON_SDA/NEON42/site_pft.csv</path>
    </pft.site>
   </inputs>
  </settings.12>
  <settings.13>
   <site>
    <id>1000004887</id>
    <met.start>2012/01/01</met.start>
    <met.end>2021/12/31</met.end>
    <lat>33.40123</lat>
    <lon>-97.57</lon>
    <name>1000004887</name>
   </site>
   <start.date>2012/01/01</start.date>
   <end.date>2021/12/31</end.date>
   <inputs>
    <met>
     <source>ERA5</source>
     <output>SIPNET</output>
     <id></id>
     <path>
      <path>/projectnb/dietzelab/dongchen/All_NEON_SDA/NEON42/ERA5_2012_2021/1000004887/ERA5.1.2012-01-01.2021-12-31.clim</path>
      <path>/projectnb/dietzelab/dongchen/All_NEON_SDA/NEON42/ERA5_2012_2021/1000004887/ERA5.10.2012-01-01.2021-12-31.clim</path>
      <path>/projectnb/dietzelab/dongchen/All_NEON_SDA/NEON42/ERA5_2012_2021/1000004887/ERA5.2.2012-01-01.2021-12-31.clim</path>
      <path>/projectnb/dietzelab/dongchen/All_NEON_SDA/NEON42/ERA5_2012_2021/1000004887/ERA5.3.2012-01-01.2021-12-31.clim</path>
      <path>/projectnb/dietzelab/dongchen/All_NEON_SDA/NEON42/ERA5_2012_2021/1000004887/ERA5.4.2012-01-01.2021-12-31.clim</path>
      <path>/projectnb/dietzelab/dongchen/All_NEON_SDA/NEON42/ERA5_2012_2021/1000004887/ERA5.5.2012-01-01.2021-12-31.clim</path>
      <path>/projectnb/dietzelab/dongchen/All_NEON_SDA/NEON42/ERA5_2012_2021/1000004887/ERA5.6.2012-01-01.2021-12-31.clim</path>
      <path>/projectnb/dietzelab/dongchen/All_NEON_SDA/NEON42/ERA5_2012_2021/1000004887/ERA5.7.2012-01-01.2021-12-31.clim</path>
      <path>/projectnb/dietzelab/dongchen/All_NEON_SDA/NEON42/ERA5_2012_2021/1000004887/ERA5.8.2012-01-01.2021-12-31.clim</path>
      <path>/projectnb/dietzelab/dongchen/All_NEON_SDA/NEON42/ERA5_2012_2021/1000004887/ERA5.9.2012-01-01.2021-12-31.clim</path>
     </path>
    </met>
    <pft.site>
     <path>/projectnb/dietzelab/dongchen/All_NEON_SDA/NEON42/site_pft.csv</path>
    </pft.site>
   </inputs>
  </settings.13>
  <settings.14>
   <site>
    <id>1000004941</id>
    <met.start>2012/01/01</met.start>
    <met.end>2021/12/31</met.end>
    <lat>37.37828</lat>
    <lon>-80.52484</lon>
    <name>1000004941</name>
   </site>
   <start.date>2012/01/01</start.date>
   <end.date>2021/12/31</end.date>
   <inputs>
    <met>
     <source>ERA5</source>
     <output>SIPNET</output>
     <id></id>
     <path>
      <path>/projectnb/dietzelab/dongchen/All_NEON_SDA/NEON42/ERA5_2012_2021/1000004941/ERA5.1.2012-01-01.2021-12-31.clim</path>
      <path>/projectnb/dietzelab/dongchen/All_NEON_SDA/NEON42/ERA5_2012_2021/1000004941/ERA5.10.2012-01-01.2021-12-31.clim</path>
      <path>/projectnb/dietzelab/dongchen/All_NEON_SDA/NEON42/ERA5_2012_2021/1000004941/ERA5.2.2012-01-01.2021-12-31.clim</path>
      <path>/projectnb/dietzelab/dongchen/All_NEON_SDA/NEON42/ERA5_2012_2021/1000004941/ERA5.3.2012-01-01.2021-12-31.clim</path>
      <path>/projectnb/dietzelab/dongchen/All_NEON_SDA/NEON42/ERA5_2012_2021/1000004941/ERA5.4.2012-01-01.2021-12-31.clim</path>
      <path>/projectnb/dietzelab/dongchen/All_NEON_SDA/NEON42/ERA5_2012_2021/1000004941/ERA5.5.2012-01-01.2021-12-31.clim</path>
      <path>/projectnb/dietzelab/dongchen/All_NEON_SDA/NEON42/ERA5_2012_2021/1000004941/ERA5.6.2012-01-01.2021-12-31.clim</path>
      <path>/projectnb/dietzelab/dongchen/All_NEON_SDA/NEON42/ERA5_2012_2021/1000004941/ERA5.7.2012-01-01.2021-12-31.clim</path>
      <path>/projectnb/dietzelab/dongchen/All_NEON_SDA/NEON42/ERA5_2012_2021/1000004941/ERA5.8.2012-01-01.2021-12-31.clim</path>
      <path>/projectnb/dietzelab/dongchen/All_NEON_SDA/NEON42/ERA5_2012_2021/1000004941/ERA5.9.2012-01-01.2021-12-31.clim</path>
     </path>
    </met>
    <pft.site>
     <path>/projectnb/dietzelab/dongchen/All_NEON_SDA/NEON42/site_pft.csv</path>
    </pft.site>
   </inputs>
  </settings.14>
  <settings.15>
   <site>
    <id>1000004876</id>
    <met.start>2012/01/01</met.start>
    <met.end>2021/12/31</met.end>
    <lat>31.91068</lat>
    <lon>-110.83549</lon>
    <name>1000004876</name>
   </site>
   <start.date>2012/01/01</start.date>
   <end.date>2021/12/31</end.date>
   <inputs>
    <met>
     <source>ERA5</source>
     <output>SIPNET</output>
     <id></id>
     <path>
      <path>/projectnb/dietzelab/dongchen/All_NEON_SDA/NEON42/ERA5_2012_2021/1000004876/ERA5.1.2012-01-01.2021-12-31.clim</path>
      <path>/projectnb/dietzelab/dongchen/All_NEON_SDA/NEON42/ERA5_2012_2021/1000004876/ERA5.10.2012-01-01.2021-12-31.clim</path>
      <path>/projectnb/dietzelab/dongchen/All_NEON_SDA/NEON42/ERA5_2012_2021/1000004876/ERA5.2.2012-01-01.2021-12-31.clim</path>
      <path>/projectnb/dietzelab/dongchen/All_NEON_SDA/NEON42/ERA5_2012_2021/1000004876/ERA5.3.2012-01-01.2021-12-31.clim</path>
      <path>/projectnb/dietzelab/dongchen/All_NEON_SDA/NEON42/ERA5_2012_2021/1000004876/ERA5.4.2012-01-01.2021-12-31.clim</path>
      <path>/projectnb/dietzelab/dongchen/All_NEON_SDA/NEON42/ERA5_2012_2021/1000004876/ERA5.5.2012-01-01.2021-12-31.clim</path>
      <path>/projectnb/dietzelab/dongchen/All_NEON_SDA/NEON42/ERA5_2012_2021/1000004876/ERA5.6.2012-01-01.2021-12-31.clim</path>
      <path>/projectnb/dietzelab/dongchen/All_NEON_SDA/NEON42/ERA5_2012_2021/1000004876/ERA5.7.2012-01-01.2021-12-31.clim</path>
      <path>/projectnb/dietzelab/dongchen/All_NEON_SDA/NEON42/ERA5_2012_2021/1000004876/ERA5.8.2012-01-01.2021-12-31.clim</path>
      <path>/projectnb/dietzelab/dongchen/All_NEON_SDA/NEON42/ERA5_2012_2021/1000004876/ERA5.9.2012-01-01.2021-12-31.clim</path>
     </path>
    </met>
    <pft.site>
     <path>/projectnb/dietzelab/dongchen/All_NEON_SDA/NEON42/site_pft.csv</path>
    </pft.site>
   </inputs>
  </settings.15>
  <settings.16>
   <site>
    <id>1000004929</id>
    <met.start>2012/01/01</met.start>
    <met.end>2021/12/31</met.end>
    <lat>47.12823</lat>
    <lon>-99.24136</lon>
    <name>1000004929</name>
   </site>
   <start.date>2012/01/01</start.date>
   <end.date>2021/12/31</end.date>
   <inputs>
    <met>
     <source>ERA5</source>
     <output>SIPNET</output>
     <id></id>
     <path>
      <path>/projectnb/dietzelab/dongchen/All_NEON_SDA/NEON42/ERA5_2012_2021/1000004929/ERA5.1.2012-01-01.2021-12-31.clim</path>
      <path>/projectnb/dietzelab/dongchen/All_NEON_SDA/NEON42/ERA5_2012_2021/1000004929/ERA5.10.2012-01-01.2021-12-31.clim</path>
      <path>/projectnb/dietzelab/dongchen/All_NEON_SDA/NEON42/ERA5_2012_2021/1000004929/ERA5.2.2012-01-01.2021-12-31.clim</path>
      <path>/projectnb/dietzelab/dongchen/All_NEON_SDA/NEON42/ERA5_2012_2021/1000004929/ERA5.3.2012-01-01.2021-12-31.clim</path>
      <path>/projectnb/dietzelab/dongchen/All_NEON_SDA/NEON42/ERA5_2012_2021/1000004929/ERA5.4.2012-01-01.2021-12-31.clim</path>
      <path>/projectnb/dietzelab/dongchen/All_NEON_SDA/NEON42/ERA5_2012_2021/1000004929/ERA5.5.2012-01-01.2021-12-31.clim</path>
      <path>/projectnb/dietzelab/dongchen/All_NEON_SDA/NEON42/ERA5_2012_2021/1000004929/ERA5.6.2012-01-01.2021-12-31.clim</path>
      <path>/projectnb/dietzelab/dongchen/All_NEON_SDA/NEON42/ERA5_2012_2021/1000004929/ERA5.7.2012-01-01.2021-12-31.clim</path>
      <path>/projectnb/dietzelab/dongchen/All_NEON_SDA/NEON42/ERA5_2012_2021/1000004929/ERA5.8.2012-01-01.2021-12-31.clim</path>
      <path>/projectnb/dietzelab/dongchen/All_NEON_SDA/NEON42/ERA5_2012_2021/1000004929/ERA5.9.2012-01-01.2021-12-31.clim</path>
     </path>
    </met>
    <pft.site>
     <path>/projectnb/dietzelab/dongchen/All_NEON_SDA/NEON42/site_pft.csv</path>
    </pft.site>
   </inputs>
  </settings.16>
  <settings.17>
   <site>
    <id>1000004890</id>
    <met.start>2012/01/01</met.start>
    <met.end>2021/12/31</met.end>
    <lat>45.76243</lat>
    <lon>-122.33033</lon>
    <name>1000004890</name>
   </site>
   <start.date>2012/01/01</start.date>
   <end.date>2021/12/31</end.date>
   <inputs>
    <met>
     <source>ERA5</source>
     <output>SIPNET</output>
     <id></id>
     <path>
      <path>/projectnb/dietzelab/dongchen/All_NEON_SDA/NEON42/ERA5_2012_2021/1000004890/ERA5.1.2012-01-01.2021-12-31.clim</path>
      <path>/projectnb/dietzelab/dongchen/All_NEON_SDA/NEON42/ERA5_2012_2021/1000004890/ERA5.10.2012-01-01.2021-12-31.clim</path>
      <path>/projectnb/dietzelab/dongchen/All_NEON_SDA/NEON42/ERA5_2012_2021/1000004890/ERA5.2.2012-01-01.2021-12-31.clim</path>
      <path>/projectnb/dietzelab/dongchen/All_NEON_SDA/NEON42/ERA5_2012_2021/1000004890/ERA5.3.2012-01-01.2021-12-31.clim</path>
      <path>/projectnb/dietzelab/dongchen/All_NEON_SDA/NEON42/ERA5_2012_2021/1000004890/ERA5.4.2012-01-01.2021-12-31.clim</path>
      <path>/projectnb/dietzelab/dongchen/All_NEON_SDA/NEON42/ERA5_2012_2021/1000004890/ERA5.5.2012-01-01.2021-12-31.clim</path>
      <path>/projectnb/dietzelab/dongchen/All_NEON_SDA/NEON42/ERA5_2012_2021/1000004890/ERA5.6.2012-01-01.2021-12-31.clim</path>
      <path>/projectnb/dietzelab/dongchen/All_NEON_SDA/NEON42/ERA5_2012_2021/1000004890/ERA5.7.2012-01-01.2021-12-31.clim</path>
      <path>/projectnb/dietzelab/dongchen/All_NEON_SDA/NEON42/ERA5_2012_2021/1000004890/ERA5.8.2012-01-01.2021-12-31.clim</path>
      <path>/projectnb/dietzelab/dongchen/All_NEON_SDA/NEON42/ERA5_2012_2021/1000004890/ERA5.9.2012-01-01.2021-12-31.clim</path>
     </path>
    </met>
    <pft.site>
     <path>/projectnb/dietzelab/dongchen/All_NEON_SDA/NEON42/site_pft.csv</path>
    </pft.site>
   </inputs>
  </settings.17>
  <settings.18>
   <site>
    <id>1000004889</id>
    <met.start>2012/01/01</met.start>
    <met.end>2021/12/31</met.end>
    <lat>45.82049</lat>
    <lon>-121.95191</lon>
    <name>1000004889</name>
   </site>
   <start.date>2012/01/01</start.date>
   <end.date>2021/12/31</end.date>
   <inputs>
    <met>
     <source>ERA5</source>
     <output>SIPNET</output>
     <id></id>
     <path>
      <path>/projectnb/dietzelab/dongchen/All_NEON_SDA/NEON42/ERA5_2012_2021/1000004889/ERA5.1.2012-01-01.2021-12-31.clim</path>
      <path>/projectnb/dietzelab/dongchen/All_NEON_SDA/NEON42/ERA5_2012_2021/1000004889/ERA5.10.2012-01-01.2021-12-31.clim</path>
      <path>/projectnb/dietzelab/dongchen/All_NEON_SDA/NEON42/ERA5_2012_2021/1000004889/ERA5.2.2012-01-01.2021-12-31.clim</path>
      <path>/projectnb/dietzelab/dongchen/All_NEON_SDA/NEON42/ERA5_2012_2021/1000004889/ERA5.3.2012-01-01.2021-12-31.clim</path>
      <path>/projectnb/dietzelab/dongchen/All_NEON_SDA/NEON42/ERA5_2012_2021/1000004889/ERA5.4.2012-01-01.2021-12-31.clim</path>
      <path>/projectnb/dietzelab/dongchen/All_NEON_SDA/NEON42/ERA5_2012_2021/1000004889/ERA5.5.2012-01-01.2021-12-31.clim</path>
      <path>/projectnb/dietzelab/dongchen/All_NEON_SDA/NEON42/ERA5_2012_2021/1000004889/ERA5.6.2012-01-01.2021-12-31.clim</path>
      <path>/projectnb/dietzelab/dongchen/All_NEON_SDA/NEON42/ERA5_2012_2021/1000004889/ERA5.7.2012-01-01.2021-12-31.clim</path>
      <path>/projectnb/dietzelab/dongchen/All_NEON_SDA/NEON42/ERA5_2012_2021/1000004889/ERA5.8.2012-01-01.2021-12-31.clim</path>
      <path>/projectnb/dietzelab/dongchen/All_NEON_SDA/NEON42/ERA5_2012_2021/1000004889/ERA5.9.2012-01-01.2021-12-31.clim</path>
     </path>
    </met>
    <pft.site>
     <path>/projectnb/dietzelab/dongchen/All_NEON_SDA/NEON42/site_pft.csv</path>
    </pft.site>
   </inputs>
  </settings.18>
  <settings.19>
   <site>
    <id>1000004940</id>
    <met.start>2012/01/01</met.start>
    <met.end>2021/12/31</met.end>
    <lat>35.96412</lat>
    <lon>-84.2826</lon>
    <name>1000004940</name>
   </site>
   <start.date>2012/01/01</start.date>
   <end.date>2021/12/31</end.date>
   <inputs>
    <met>
     <source>ERA5</source>
     <output>SIPNET</output>
     <id></id>
     <path>
      <path>/projectnb/dietzelab/dongchen/All_NEON_SDA/NEON42/ERA5_2012_2021/1000004940/ERA5.1.2012-01-01.2021-12-31.clim</path>
      <path>/projectnb/dietzelab/dongchen/All_NEON_SDA/NEON42/ERA5_2012_2021/1000004940/ERA5.10.2012-01-01.2021-12-31.clim</path>
      <path>/projectnb/dietzelab/dongchen/All_NEON_SDA/NEON42/ERA5_2012_2021/1000004940/ERA5.2.2012-01-01.2021-12-31.clim</path>
      <path>/projectnb/dietzelab/dongchen/All_NEON_SDA/NEON42/ERA5_2012_2021/1000004940/ERA5.3.2012-01-01.2021-12-31.clim</path>
      <path>/projectnb/dietzelab/dongchen/All_NEON_SDA/NEON42/ERA5_2012_2021/1000004940/ERA5.4.2012-01-01.2021-12-31.clim</path>
      <path>/projectnb/dietzelab/dongchen/All_NEON_SDA/NEON42/ERA5_2012_2021/1000004940/ERA5.5.2012-01-01.2021-12-31.clim</path>
      <path>/projectnb/dietzelab/dongchen/All_NEON_SDA/NEON42/ERA5_2012_2021/1000004940/ERA5.6.2012-01-01.2021-12-31.clim</path>
      <path>/projectnb/dietzelab/dongchen/All_NEON_SDA/NEON42/ERA5_2012_2021/1000004940/ERA5.7.2012-01-01.2021-12-31.clim</path>
      <path>/projectnb/dietzelab/dongchen/All_NEON_SDA/NEON42/ERA5_2012_2021/1000004940/ERA5.8.2012-01-01.2021-12-31.clim</path>
      <path>/projectnb/dietzelab/dongchen/All_NEON_SDA/NEON42/ERA5_2012_2021/1000004940/ERA5.9.2012-01-01.2021-12-31.clim</path>
     </path>
    </met>
    <pft.site>
     <path>/projectnb/dietzelab/dongchen/All_NEON_SDA/NEON42/site_pft.csv</path>
    </pft.site>
   </inputs>
  </settings.19>
  <settings.20>
   <site>
    <id>1000004905</id>
    <met.start>2012/01/01</met.start>
    <met.end>2021/12/31</met.end>
    <lat>40.81553</lat>
    <lon>-104.7456</lon>
    <name>1000004905</name>
   </site>
   <start.date>2012/01/01</start.date>
   <end.date>2021/12/31</end.date>
   <inputs>
    <met>
     <source>ERA5</source>
     <output>SIPNET</output>
     <id></id>
     <path>
      <path>/projectnb/dietzelab/dongchen/All_NEON_SDA/NEON42/ERA5_2012_2021/1000004905/ERA5.1.2012-01-01.2021-12-31.clim</path>
      <path>/projectnb/dietzelab/dongchen/All_NEON_SDA/NEON42/ERA5_2012_2021/1000004905/ERA5.10.2012-01-01.2021-12-31.clim</path>
      <path>/projectnb/dietzelab/dongchen/All_NEON_SDA/NEON42/ERA5_2012_2021/1000004905/ERA5.2.2012-01-01.2021-12-31.clim</path>
      <path>/projectnb/dietzelab/dongchen/All_NEON_SDA/NEON42/ERA5_2012_2021/1000004905/ERA5.3.2012-01-01.2021-12-31.clim</path>
      <path>/projectnb/dietzelab/dongchen/All_NEON_SDA/NEON42/ERA5_2012_2021/1000004905/ERA5.4.2012-01-01.2021-12-31.clim</path>
      <path>/projectnb/dietzelab/dongchen/All_NEON_SDA/NEON42/ERA5_2012_2021/1000004905/ERA5.5.2012-01-01.2021-12-31.clim</path>
      <path>/projectnb/dietzelab/dongchen/All_NEON_SDA/NEON42/ERA5_2012_2021/1000004905/ERA5.6.2012-01-01.2021-12-31.clim</path>
      <path>/projectnb/dietzelab/dongchen/All_NEON_SDA/NEON42/ERA5_2012_2021/1000004905/ERA5.7.2012-01-01.2021-12-31.clim</path>
      <path>/projectnb/dietzelab/dongchen/All_NEON_SDA/NEON42/ERA5_2012_2021/1000004905/ERA5.8.2012-01-01.2021-12-31.clim</path>
      <path>/projectnb/dietzelab/dongchen/All_NEON_SDA/NEON42/ERA5_2012_2021/1000004905/ERA5.9.2012-01-01.2021-12-31.clim</path>
     </path>
    </met>
    <pft.site>
     <path>/projectnb/dietzelab/dongchen/All_NEON_SDA/NEON42/site_pft.csv</path>
    </pft.site>
   </inputs>
  </settings.20>
  <settings.21>
   <site>
    <id>1000004878</id>
    <met.start>2012/01/01</met.start>
    <met.end>2021/12/31</met.end>
    <lat>40.05425</lat>
    <lon>-105.58237</lon>
    <name>1000004878</name>
   </site>
   <start.date>2012/01/01</start.date>
   <end.date>2021/12/31</end.date>
   <inputs>
    <met>
     <source>ERA5</source>
     <output>SIPNET</output>
     <id></id>
     <path>
      <path>/projectnb/dietzelab/dongchen/All_NEON_SDA/NEON42/ERA5_2012_2021/1000004878/ERA5.1.2012-01-01.2021-12-31.clim</path>
      <path>/projectnb/dietzelab/dongchen/All_NEON_SDA/NEON42/ERA5_2012_2021/1000004878/ERA5.10.2012-01-01.2021-12-31.clim</path>
      <path>/projectnb/dietzelab/dongchen/All_NEON_SDA/NEON42/ERA5_2012_2021/1000004878/ERA5.2.2012-01-01.2021-12-31.clim</path>
      <path>/projectnb/dietzelab/dongchen/All_NEON_SDA/NEON42/ERA5_2012_2021/1000004878/ERA5.3.2012-01-01.2021-12-31.clim</path>
      <path>/projectnb/dietzelab/dongchen/All_NEON_SDA/NEON42/ERA5_2012_2021/1000004878/ERA5.4.2012-01-01.2021-12-31.clim</path>
      <path>/projectnb/dietzelab/dongchen/All_NEON_SDA/NEON42/ERA5_2012_2021/1000004878/ERA5.5.2012-01-01.2021-12-31.clim</path>
      <path>/projectnb/dietzelab/dongchen/All_NEON_SDA/NEON42/ERA5_2012_2021/1000004878/ERA5.6.2012-01-01.2021-12-31.clim</path>
      <path>/projectnb/dietzelab/dongchen/All_NEON_SDA/NEON42/ERA5_2012_2021/1000004878/ERA5.7.2012-01-01.2021-12-31.clim</path>
      <path>/projectnb/dietzelab/dongchen/All_NEON_SDA/NEON42/ERA5_2012_2021/1000004878/ERA5.8.2012-01-01.2021-12-31.clim</path>
      <path>/projectnb/dietzelab/dongchen/All_NEON_SDA/NEON42/ERA5_2012_2021/1000004878/ERA5.9.2012-01-01.2021-12-31.clim</path>
     </path>
    </met>
    <pft.site>
     <path>/projectnb/dietzelab/dongchen/All_NEON_SDA/NEON42/site_pft.csv</path>
    </pft.site>
   </inputs>
  </settings.21>
  <settings.22>
   <site>
    <id>1000004928</id>
    <met.start>2012/01/01</met.start>
    <met.end>2021/12/31</met.end>
    <lat>40.27591</lat>
    <lon>-105.54592</lon>
    <name>1000004928</name>
   </site>
   <start.date>2012/01/01</start.date>
   <end.date>2021/12/31</end.date>
   <inputs>
    <met>
     <source>ERA5</source>
     <output>SIPNET</output>
     <id></id>
     <path>
      <path>/projectnb/dietzelab/dongchen/All_NEON_SDA/NEON42/ERA5_2012_2021/1000004928/ERA5.1.2012-01-01.2021-12-31.clim</path>
      <path>/projectnb/dietzelab/dongchen/All_NEON_SDA/NEON42/ERA5_2012_2021/1000004928/ERA5.10.2012-01-01.2021-12-31.clim</path>
      <path>/projectnb/dietzelab/dongchen/All_NEON_SDA/NEON42/ERA5_2012_2021/1000004928/ERA5.2.2012-01-01.2021-12-31.clim</path>
      <path>/projectnb/dietzelab/dongchen/All_NEON_SDA/NEON42/ERA5_2012_2021/1000004928/ERA5.3.2012-01-01.2021-12-31.clim</path>
      <path>/projectnb/dietzelab/dongchen/All_NEON_SDA/NEON42/ERA5_2012_2021/1000004928/ERA5.4.2012-01-01.2021-12-31.clim</path>
      <path>/projectnb/dietzelab/dongchen/All_NEON_SDA/NEON42/ERA5_2012_2021/1000004928/ERA5.5.2012-01-01.2021-12-31.clim</path>
      <path>/projectnb/dietzelab/dongchen/All_NEON_SDA/NEON42/ERA5_2012_2021/1000004928/ERA5.6.2012-01-01.2021-12-31.clim</path>
      <path>/projectnb/dietzelab/dongchen/All_NEON_SDA/NEON42/ERA5_2012_2021/1000004928/ERA5.7.2012-01-01.2021-12-31.clim</path>
      <path>/projectnb/dietzelab/dongchen/All_NEON_SDA/NEON42/ERA5_2012_2021/1000004928/ERA5.8.2012-01-01.2021-12-31.clim</path>
      <path>/projectnb/dietzelab/dongchen/All_NEON_SDA/NEON42/ERA5_2012_2021/1000004928/ERA5.9.2012-01-01.2021-12-31.clim</path>
     </path>
    </met>
    <pft.site>
     <path>/projectnb/dietzelab/dongchen/All_NEON_SDA/NEON42/site_pft.csv</path>
    </pft.site>
   </inputs>
  </settings.22>
  <settings.23>
   <site>
    <id>1000004916</id>
    <met.start>2012/01/01</met.start>
    <met.end>2021/12/31</met.end>
    <lat>29.68927</lat>
    <lon>-81.99343</lon>
    <name>1000004916</name>
   </site>
   <start.date>2012/01/01</start.date>
   <end.date>2021/12/31</end.date>
   <inputs>
    <met>
     <source>ERA5</source>
     <output>SIPNET</output>
     <id></id>
     <path>
      <path>/projectnb/dietzelab/dongchen/All_NEON_SDA/NEON42/ERA5_2012_2021/1000004916/ERA5.1.2012-01-01.2021-12-31.clim</path>
      <path>/projectnb/dietzelab/dongchen/All_NEON_SDA/NEON42/ERA5_2012_2021/1000004916/ERA5.10.2012-01-01.2021-12-31.clim</path>
      <path>/projectnb/dietzelab/dongchen/All_NEON_SDA/NEON42/ERA5_2012_2021/1000004916/ERA5.2.2012-01-01.2021-12-31.clim</path>
      <path>/projectnb/dietzelab/dongchen/All_NEON_SDA/NEON42/ERA5_2012_2021/1000004916/ERA5.3.2012-01-01.2021-12-31.clim</path>
      <path>/projectnb/dietzelab/dongchen/All_NEON_SDA/NEON42/ERA5_2012_2021/1000004916/ERA5.4.2012-01-01.2021-12-31.clim</path>
      <path>/projectnb/dietzelab/dongchen/All_NEON_SDA/NEON42/ERA5_2012_2021/1000004916/ERA5.5.2012-01-01.2021-12-31.clim</path>
      <path>/projectnb/dietzelab/dongchen/All_NEON_SDA/NEON42/ERA5_2012_2021/1000004916/ERA5.6.2012-01-01.2021-12-31.clim</path>
      <path>/projectnb/dietzelab/dongchen/All_NEON_SDA/NEON42/ERA5_2012_2021/1000004916/ERA5.7.2012-01-01.2021-12-31.clim</path>
      <path>/projectnb/dietzelab/dongchen/All_NEON_SDA/NEON42/ERA5_2012_2021/1000004916/ERA5.8.2012-01-01.2021-12-31.clim</path>
      <path>/projectnb/dietzelab/dongchen/All_NEON_SDA/NEON42/ERA5_2012_2021/1000004916/ERA5.9.2012-01-01.2021-12-31.clim</path>
     </path>
    </met>
    <pft.site>
     <path>/projectnb/dietzelab/dongchen/All_NEON_SDA/NEON42/site_pft.csv</path>
    </pft.site>
   </inputs>
  </settings.23>
  <settings.24>
   <site>
    <id>1000004925</id>
    <met.start>2012/01/01</met.start>
    <met.end>2021/12/31</met.end>
    <lat>39.11044</lat>
    <lon>-96.61295</lon>
    <name>1000004925</name>
   </site>
   <start.date>2012/01/01</start.date>
   <end.date>2021/12/31</end.date>
   <inputs>
    <met>
     <source>ERA5</source>
     <output>SIPNET</output>
     <id></id>
     <path>
      <path>/projectnb/dietzelab/dongchen/All_NEON_SDA/NEON42/ERA5_2012_2021/1000004925/ERA5.1.2012-01-01.2021-12-31.clim</path>
      <path>/projectnb/dietzelab/dongchen/All_NEON_SDA/NEON42/ERA5_2012_2021/1000004925/ERA5.10.2012-01-01.2021-12-31.clim</path>
      <path>/projectnb/dietzelab/dongchen/All_NEON_SDA/NEON42/ERA5_2012_2021/1000004925/ERA5.2.2012-01-01.2021-12-31.clim</path>
      <path>/projectnb/dietzelab/dongchen/All_NEON_SDA/NEON42/ERA5_2012_2021/1000004925/ERA5.3.2012-01-01.2021-12-31.clim</path>
      <path>/projectnb/dietzelab/dongchen/All_NEON_SDA/NEON42/ERA5_2012_2021/1000004925/ERA5.4.2012-01-01.2021-12-31.clim</path>
      <path>/projectnb/dietzelab/dongchen/All_NEON_SDA/NEON42/ERA5_2012_2021/1000004925/ERA5.5.2012-01-01.2021-12-31.clim</path>
      <path>/projectnb/dietzelab/dongchen/All_NEON_SDA/NEON42/ERA5_2012_2021/1000004925/ERA5.6.2012-01-01.2021-12-31.clim</path>
      <path>/projectnb/dietzelab/dongchen/All_NEON_SDA/NEON42/ERA5_2012_2021/1000004925/ERA5.7.2012-01-01.2021-12-31.clim</path>
      <path>/projectnb/dietzelab/dongchen/All_NEON_SDA/NEON42/ERA5_2012_2021/1000004925/ERA5.8.2012-01-01.2021-12-31.clim</path>
      <path>/projectnb/dietzelab/dongchen/All_NEON_SDA/NEON42/ERA5_2012_2021/1000004925/ERA5.9.2012-01-01.2021-12-31.clim</path>
     </path>
    </met>
    <pft.site>
     <path>/projectnb/dietzelab/dongchen/All_NEON_SDA/NEON42/site_pft.csv</path>
    </pft.site>
   </inputs>
  </settings.24>
  <settings.25>
   <site>
    <id>1000004881</id>
    <met.start>2012/01/01</met.start>
    <met.end>2021/12/31</met.end>
    <lat>38.24833</lat>
    <lon>-109.38827</lon>
    <name>1000004881</name>
   </site>
   <start.date>2012/01/01</start.date>
   <end.date>2021/12/31</end.date>
   <inputs>
    <met>
     <source>ERA5</source>
     <output>SIPNET</output>
     <id></id>
     <path>
      <path>/projectnb/dietzelab/dongchen/All_NEON_SDA/NEON42/ERA5_2012_2021/1000004881/ERA5.1.2012-01-01.2021-12-31.clim</path>
      <path>/projectnb/dietzelab/dongchen/All_NEON_SDA/NEON42/ERA5_2012_2021/1000004881/ERA5.10.2012-01-01.2021-12-31.clim</path>
      <path>/projectnb/dietzelab/dongchen/All_NEON_SDA/NEON42/ERA5_2012_2021/1000004881/ERA5.2.2012-01-01.2021-12-31.clim</path>
      <path>/projectnb/dietzelab/dongchen/All_NEON_SDA/NEON42/ERA5_2012_2021/1000004881/ERA5.3.2012-01-01.2021-12-31.clim</path>
      <path>/projectnb/dietzelab/dongchen/All_NEON_SDA/NEON42/ERA5_2012_2021/1000004881/ERA5.4.2012-01-01.2021-12-31.clim</path>
      <path>/projectnb/dietzelab/dongchen/All_NEON_SDA/NEON42/ERA5_2012_2021/1000004881/ERA5.5.2012-01-01.2021-12-31.clim</path>
      <path>/projectnb/dietzelab/dongchen/All_NEON_SDA/NEON42/ERA5_2012_2021/1000004881/ERA5.6.2012-01-01.2021-12-31.clim</path>
      <path>/projectnb/dietzelab/dongchen/All_NEON_SDA/NEON42/ERA5_2012_2021/1000004881/ERA5.7.2012-01-01.2021-12-31.clim</path>
      <path>/projectnb/dietzelab/dongchen/All_NEON_SDA/NEON42/ERA5_2012_2021/1000004881/ERA5.8.2012-01-01.2021-12-31.clim</path>
      <path>/projectnb/dietzelab/dongchen/All_NEON_SDA/NEON42/ERA5_2012_2021/1000004881/ERA5.9.2012-01-01.2021-12-31.clim</path>
     </path>
    </met>
    <pft.site>
     <path>/projectnb/dietzelab/dongchen/All_NEON_SDA/NEON42/site_pft.csv</path>
    </pft.site>
   </inputs>
  </settings.25>
  <settings.26>
   <site>
    <id>1000004877</id>
    <met.start>2012/01/01</met.start>
    <met.end>2021/12/31</met.end>
    <lat>32.59068</lat>
    <lon>-106.84254</lon>
    <name>1000004877</name>
   </site>
   <start.date>2012/01/01</start.date>
   <end.date>2021/12/31</end.date>
   <inputs>
    <met>
     <source>ERA5</source>
     <output>SIPNET</output>
     <id></id>
     <path>
      <path>/projectnb/dietzelab/dongchen/All_NEON_SDA/NEON42/ERA5_2012_2021/1000004877/ERA5.1.2012-01-01.2021-12-31.clim</path>
      <path>/projectnb/dietzelab/dongchen/All_NEON_SDA/NEON42/ERA5_2012_2021/1000004877/ERA5.10.2012-01-01.2021-12-31.clim</path>
      <path>/projectnb/dietzelab/dongchen/All_NEON_SDA/NEON42/ERA5_2012_2021/1000004877/ERA5.2.2012-01-01.2021-12-31.clim</path>
      <path>/projectnb/dietzelab/dongchen/All_NEON_SDA/NEON42/ERA5_2012_2021/1000004877/ERA5.3.2012-01-01.2021-12-31.clim</path>
      <path>/projectnb/dietzelab/dongchen/All_NEON_SDA/NEON42/ERA5_2012_2021/1000004877/ERA5.4.2012-01-01.2021-12-31.clim</path>
      <path>/projectnb/dietzelab/dongchen/All_NEON_SDA/NEON42/ERA5_2012_2021/1000004877/ERA5.5.2012-01-01.2021-12-31.clim</path>
      <path>/projectnb/dietzelab/dongchen/All_NEON_SDA/NEON42/ERA5_2012_2021/1000004877/ERA5.6.2012-01-01.2021-12-31.clim</path>
      <path>/projectnb/dietzelab/dongchen/All_NEON_SDA/NEON42/ERA5_2012_2021/1000004877/ERA5.7.2012-01-01.2021-12-31.clim</path>
      <path>/projectnb/dietzelab/dongchen/All_NEON_SDA/NEON42/ERA5_2012_2021/1000004877/ERA5.8.2012-01-01.2021-12-31.clim</path>
      <path>/projectnb/dietzelab/dongchen/All_NEON_SDA/NEON42/ERA5_2012_2021/1000004877/ERA5.9.2012-01-01.2021-12-31.clim</path>
     </path>
    </met>
    <pft.site>
     <path>/projectnb/dietzelab/dongchen/All_NEON_SDA/NEON42/site_pft.csv</path>
    </pft.site>
   </inputs>
  </settings.26>
  <settings.27>
   <site>
    <id>1000004902</id>
    <met.start>2012/01/01</met.start>
    <met.end>2021/12/31</met.end>
    <lat>31.85388</lat>
    <lon>-88.16122</lon>
    <name>1000004902</name>
   </site>
   <start.date>2012/01/01</start.date>
   <end.date>2021/12/31</end.date>
   <inputs>
    <met>
     <source>ERA5</source>
     <output>SIPNET</output>
     <id></id>
     <path>
      <path>/projectnb/dietzelab/dongchen/All_NEON_SDA/NEON42/ERA5_2012_2021/1000004902/ERA5.1.2012-01-01.2021-12-31.clim</path>
      <path>/projectnb/dietzelab/dongchen/All_NEON_SDA/NEON42/ERA5_2012_2021/1000004902/ERA5.10.2012-01-01.2021-12-31.clim</path>
      <path>/projectnb/dietzelab/dongchen/All_NEON_SDA/NEON42/ERA5_2012_2021/1000004902/ERA5.2.2012-01-01.2021-12-31.clim</path>
      <path>/projectnb/dietzelab/dongchen/All_NEON_SDA/NEON42/ERA5_2012_2021/1000004902/ERA5.3.2012-01-01.2021-12-31.clim</path>
      <path>/projectnb/dietzelab/dongchen/All_NEON_SDA/NEON42/ERA5_2012_2021/1000004902/ERA5.4.2012-01-01.2021-12-31.clim</path>
      <path>/projectnb/dietzelab/dongchen/All_NEON_SDA/NEON42/ERA5_2012_2021/1000004902/ERA5.5.2012-01-01.2021-12-31.clim</path>
      <path>/projectnb/dietzelab/dongchen/All_NEON_SDA/NEON42/ERA5_2012_2021/1000004902/ERA5.6.2012-01-01.2021-12-31.clim</path>
      <path>/projectnb/dietzelab/dongchen/All_NEON_SDA/NEON42/ERA5_2012_2021/1000004902/ERA5.7.2012-01-01.2021-12-31.clim</path>
      <path>/projectnb/dietzelab/dongchen/All_NEON_SDA/NEON42/ERA5_2012_2021/1000004902/ERA5.8.2012-01-01.2021-12-31.clim</path>
      <path>/projectnb/dietzelab/dongchen/All_NEON_SDA/NEON42/ERA5_2012_2021/1000004902/ERA5.9.2012-01-01.2021-12-31.clim</path>
     </path>
    </met>
    <pft.site>
     <path>/projectnb/dietzelab/dongchen/All_NEON_SDA/NEON42/site_pft.csv</path>
    </pft.site>
   </inputs>
  </settings.27>
  <settings.28>
   <site>
    <id>1000004882</id>
    <met.start>2012/01/01</met.start>
    <met.end>2021/12/31</met.end>
    <lat>44.95348</lat>
    <lon>-110.53914</lon>
    <name>1000004882</name>
   </site>
   <start.date>2012/01/01</start.date>
   <end.date>2021/12/31</end.date>
   <inputs>
    <met>
     <source>ERA5</source>
     <output>SIPNET</output>
     <id></id>
     <path>
      <path>/projectnb/dietzelab/dongchen/All_NEON_SDA/NEON42/ERA5_2012_2021/1000004882/ERA5.1.2012-01-01.2021-12-31.clim</path>
      <path>/projectnb/dietzelab/dongchen/All_NEON_SDA/NEON42/ERA5_2012_2021/1000004882/ERA5.10.2012-01-01.2021-12-31.clim</path>
      <path>/projectnb/dietzelab/dongchen/All_NEON_SDA/NEON42/ERA5_2012_2021/1000004882/ERA5.2.2012-01-01.2021-12-31.clim</path>
      <path>/projectnb/dietzelab/dongchen/All_NEON_SDA/NEON42/ERA5_2012_2021/1000004882/ERA5.3.2012-01-01.2021-12-31.clim</path>
      <path>/projectnb/dietzelab/dongchen/All_NEON_SDA/NEON42/ERA5_2012_2021/1000004882/ERA5.4.2012-01-01.2021-12-31.clim</path>
      <path>/projectnb/dietzelab/dongchen/All_NEON_SDA/NEON42/ERA5_2012_2021/1000004882/ERA5.5.2012-01-01.2021-12-31.clim</path>
      <path>/projectnb/dietzelab/dongchen/All_NEON_SDA/NEON42/ERA5_2012_2021/1000004882/ERA5.6.2012-01-01.2021-12-31.clim</path>
      <path>/projectnb/dietzelab/dongchen/All_NEON_SDA/NEON42/ERA5_2012_2021/1000004882/ERA5.7.2012-01-01.2021-12-31.clim</path>
      <path>/projectnb/dietzelab/dongchen/All_NEON_SDA/NEON42/ERA5_2012_2021/1000004882/ERA5.8.2012-01-01.2021-12-31.clim</path>
      <path>/projectnb/dietzelab/dongchen/All_NEON_SDA/NEON42/ERA5_2012_2021/1000004882/ERA5.9.2012-01-01.2021-12-31.clim</path>
     </path>
    </met>
    <pft.site>
     <path>/projectnb/dietzelab/dongchen/All_NEON_SDA/NEON42/site_pft.csv</path>
    </pft.site>
   </inputs>
  </settings.28>
  <settings.29>
   <site>
    <id>1000004943</id>
    <met.start>2012/01/01</met.start>
    <met.end>2021/12/31</met.end>
    <lat>35.68896</lat>
    <lon>-83.50195</lon>
    <name>1000004943</name>
   </site>
   <start.date>2012/01/01</start.date>
   <end.date>2021/12/31</end.date>
   <inputs>
    <met>
     <source>ERA5</source>
     <output>SIPNET</output>
     <id></id>
     <path>
      <path>/projectnb/dietzelab/dongchen/All_NEON_SDA/NEON42/ERA5_2012_2021/1000004943/ERA5.1.2012-01-01.2021-12-31.clim</path>
      <path>/projectnb/dietzelab/dongchen/All_NEON_SDA/NEON42/ERA5_2012_2021/1000004943/ERA5.10.2012-01-01.2021-12-31.clim</path>
      <path>/projectnb/dietzelab/dongchen/All_NEON_SDA/NEON42/ERA5_2012_2021/1000004943/ERA5.2.2012-01-01.2021-12-31.clim</path>
      <path>/projectnb/dietzelab/dongchen/All_NEON_SDA/NEON42/ERA5_2012_2021/1000004943/ERA5.3.2012-01-01.2021-12-31.clim</path>
      <path>/projectnb/dietzelab/dongchen/All_NEON_SDA/NEON42/ERA5_2012_2021/1000004943/ERA5.4.2012-01-01.2021-12-31.clim</path>
      <path>/projectnb/dietzelab/dongchen/All_NEON_SDA/NEON42/ERA5_2012_2021/1000004943/ERA5.5.2012-01-01.2021-12-31.clim</path>
      <path>/projectnb/dietzelab/dongchen/All_NEON_SDA/NEON42/ERA5_2012_2021/1000004943/ERA5.6.2012-01-01.2021-12-31.clim</path>
      <path>/projectnb/dietzelab/dongchen/All_NEON_SDA/NEON42/ERA5_2012_2021/1000004943/ERA5.7.2012-01-01.2021-12-31.clim</path>
      <path>/projectnb/dietzelab/dongchen/All_NEON_SDA/NEON42/ERA5_2012_2021/1000004943/ERA5.8.2012-01-01.2021-12-31.clim</path>
      <path>/projectnb/dietzelab/dongchen/All_NEON_SDA/NEON42/ERA5_2012_2021/1000004943/ERA5.9.2012-01-01.2021-12-31.clim</path>
     </path>
    </met>
    <pft.site>
     <path>/projectnb/dietzelab/dongchen/All_NEON_SDA/NEON42/site_pft.csv</path>
    </pft.site>
   </inputs>
  </settings.29>
  <settings.30>
   <site>
    <id>1000004907</id>
    <met.start>2012/01/01</met.start>
    <met.end>2021/12/31</met.end>
    <lat>40.4619</lat>
    <lon>-103.0293</lon>
    <name>1000004907</name>
   </site>
   <start.date>2012/01/01</start.date>
   <end.date>2021/12/31</end.date>
   <inputs>
    <met>
     <source>ERA5</source>
     <output>SIPNET</output>
     <id></id>
     <path>
      <path>/projectnb/dietzelab/dongchen/All_NEON_SDA/NEON42/ERA5_2012_2021/1000004907/ERA5.1.2012-01-01.2021-12-31.clim</path>
      <path>/projectnb/dietzelab/dongchen/All_NEON_SDA/NEON42/ERA5_2012_2021/1000004907/ERA5.10.2012-01-01.2021-12-31.clim</path>
      <path>/projectnb/dietzelab/dongchen/All_NEON_SDA/NEON42/ERA5_2012_2021/1000004907/ERA5.2.2012-01-01.2021-12-31.clim</path>
      <path>/projectnb/dietzelab/dongchen/All_NEON_SDA/NEON42/ERA5_2012_2021/1000004907/ERA5.3.2012-01-01.2021-12-31.clim</path>
      <path>/projectnb/dietzelab/dongchen/All_NEON_SDA/NEON42/ERA5_2012_2021/1000004907/ERA5.4.2012-01-01.2021-12-31.clim</path>
      <path>/projectnb/dietzelab/dongchen/All_NEON_SDA/NEON42/ERA5_2012_2021/1000004907/ERA5.5.2012-01-01.2021-12-31.clim</path>
      <path>/projectnb/dietzelab/dongchen/All_NEON_SDA/NEON42/ERA5_2012_2021/1000004907/ERA5.6.2012-01-01.2021-12-31.clim</path>
      <path>/projectnb/dietzelab/dongchen/All_NEON_SDA/NEON42/ERA5_2012_2021/1000004907/ERA5.7.2012-01-01.2021-12-31.clim</path>
      <path>/projectnb/dietzelab/dongchen/All_NEON_SDA/NEON42/ERA5_2012_2021/1000004907/ERA5.8.2012-01-01.2021-12-31.clim</path>
      <path>/projectnb/dietzelab/dongchen/All_NEON_SDA/NEON42/ERA5_2012_2021/1000004907/ERA5.9.2012-01-01.2021-12-31.clim</path>
     </path>
    </met>
    <pft.site>
     <path>/projectnb/dietzelab/dongchen/All_NEON_SDA/NEON42/site_pft.csv</path>
    </pft.site>
   </inputs>
  </settings.30>
  <settings.31>
   <site>
    <id>1000004933</id>
    <met.start>2012/01/01</met.start>
    <met.end>2021/12/31</met.end>
    <lat>47.16165</lat>
    <lon>-99.10656</lon>
    <name>1000004933</name>
   </site>
   <start.date>2012/01/01</start.date>
   <end.date>2021/12/31</end.date>
   <inputs>
    <met>
     <source>ERA5</source>
     <output>SIPNET</output>
     <id></id>
     <path>
      <path>/projectnb/dietzelab/dongchen/All_NEON_SDA/NEON42/ERA5_2012_2021/1000004933/ERA5.1.2012-01-01.2021-12-31.clim</path>
      <path>/projectnb/dietzelab/dongchen/All_NEON_SDA/NEON42/ERA5_2012_2021/1000004933/ERA5.10.2012-01-01.2021-12-31.clim</path>
      <path>/projectnb/dietzelab/dongchen/All_NEON_SDA/NEON42/ERA5_2012_2021/1000004933/ERA5.2.2012-01-01.2021-12-31.clim</path>
      <path>/projectnb/dietzelab/dongchen/All_NEON_SDA/NEON42/ERA5_2012_2021/1000004933/ERA5.3.2012-01-01.2021-12-31.clim</path>
      <path>/projectnb/dietzelab/dongchen/All_NEON_SDA/NEON42/ERA5_2012_2021/1000004933/ERA5.4.2012-01-01.2021-12-31.clim</path>
      <path>/projectnb/dietzelab/dongchen/All_NEON_SDA/NEON42/ERA5_2012_2021/1000004933/ERA5.5.2012-01-01.2021-12-31.clim</path>
      <path>/projectnb/dietzelab/dongchen/All_NEON_SDA/NEON42/ERA5_2012_2021/1000004933/ERA5.6.2012-01-01.2021-12-31.clim</path>
      <path>/projectnb/dietzelab/dongchen/All_NEON_SDA/NEON42/ERA5_2012_2021/1000004933/ERA5.7.2012-01-01.2021-12-31.clim</path>
      <path>/projectnb/dietzelab/dongchen/All_NEON_SDA/NEON42/ERA5_2012_2021/1000004933/ERA5.8.2012-01-01.2021-12-31.clim</path>
      <path>/projectnb/dietzelab/dongchen/All_NEON_SDA/NEON42/ERA5_2012_2021/1000004933/ERA5.9.2012-01-01.2021-12-31.clim</path>
     </path>
    </met>
    <pft.site>
     <path>/projectnb/dietzelab/dongchen/All_NEON_SDA/NEON42/site_pft.csv</path>
    </pft.site>
   </inputs>
  </settings.31>
  <settings.32>
   <site>
    <id>1000004922</id>
    <met.start>2012/01/01</met.start>
    <met.end>2021/12/31</met.end>
    <lat>38.89292</lat>
    <lon>-78.1395</lon>
    <name>1000004922</name>
   </site>
   <start.date>2012/01/01</start.date>
   <end.date>2021/12/31</end.date>
   <inputs>
    <met>
     <source>ERA5</source>
     <output>SIPNET</output>
     <id></id>
     <path>
      <path>/projectnb/dietzelab/dongchen/All_NEON_SDA/NEON42/ERA5_2012_2021/1000004922/ERA5.1.2012-01-01.2021-12-31.clim</path>
      <path>/projectnb/dietzelab/dongchen/All_NEON_SDA/NEON42/ERA5_2012_2021/1000004922/ERA5.10.2012-01-01.2021-12-31.clim</path>
      <path>/projectnb/dietzelab/dongchen/All_NEON_SDA/NEON42/ERA5_2012_2021/1000004922/ERA5.2.2012-01-01.2021-12-31.clim</path>
      <path>/projectnb/dietzelab/dongchen/All_NEON_SDA/NEON42/ERA5_2012_2021/1000004922/ERA5.3.2012-01-01.2021-12-31.clim</path>
      <path>/projectnb/dietzelab/dongchen/All_NEON_SDA/NEON42/ERA5_2012_2021/1000004922/ERA5.4.2012-01-01.2021-12-31.clim</path>
      <path>/projectnb/dietzelab/dongchen/All_NEON_SDA/NEON42/ERA5_2012_2021/1000004922/ERA5.5.2012-01-01.2021-12-31.clim</path>
      <path>/projectnb/dietzelab/dongchen/All_NEON_SDA/NEON42/ERA5_2012_2021/1000004922/ERA5.6.2012-01-01.2021-12-31.clim</path>
      <path>/projectnb/dietzelab/dongchen/All_NEON_SDA/NEON42/ERA5_2012_2021/1000004922/ERA5.7.2012-01-01.2021-12-31.clim</path>
      <path>/projectnb/dietzelab/dongchen/All_NEON_SDA/NEON42/ERA5_2012_2021/1000004922/ERA5.8.2012-01-01.2021-12-31.clim</path>
      <path>/projectnb/dietzelab/dongchen/All_NEON_SDA/NEON42/ERA5_2012_2021/1000004922/ERA5.9.2012-01-01.2021-12-31.clim</path>
     </path>
    </met>
    <pft.site>
     <path>/projectnb/dietzelab/dongchen/All_NEON_SDA/NEON42/site_pft.csv</path>
    </pft.site>
   </inputs>
  </settings.32>
  <settings.33>
   <site>
    <id>1000004900</id>
    <met.start>2012/01/01</met.start>
    <met.end>2021/12/31</met.end>
    <lat>37.03337</lat>
    <lon>-119.26219</lon>
    <name>1000004900</name>
   </site>
   <start.date>2012/01/01</start.date>
   <end.date>2021/12/31</end.date>
   <inputs>
    <met>
     <source>ERA5</source>
     <output>SIPNET</output>
     <id></id>
     <path>
      <path>/projectnb/dietzelab/dongchen/All_NEON_SDA/NEON42/ERA5_2012_2021/1000004900/ERA5.1.2012-01-01.2021-12-31.clim</path>
      <path>/projectnb/dietzelab/dongchen/All_NEON_SDA/NEON42/ERA5_2012_2021/1000004900/ERA5.10.2012-01-01.2021-12-31.clim</path>
      <path>/projectnb/dietzelab/dongchen/All_NEON_SDA/NEON42/ERA5_2012_2021/1000004900/ERA5.2.2012-01-01.2021-12-31.clim</path>
      <path>/projectnb/dietzelab/dongchen/All_NEON_SDA/NEON42/ERA5_2012_2021/1000004900/ERA5.3.2012-01-01.2021-12-31.clim</path>
      <path>/projectnb/dietzelab/dongchen/All_NEON_SDA/NEON42/ERA5_2012_2021/1000004900/ERA5.4.2012-01-01.2021-12-31.clim</path>
      <path>/projectnb/dietzelab/dongchen/All_NEON_SDA/NEON42/ERA5_2012_2021/1000004900/ERA5.5.2012-01-01.2021-12-31.clim</path>
      <path>/projectnb/dietzelab/dongchen/All_NEON_SDA/NEON42/ERA5_2012_2021/1000004900/ERA5.6.2012-01-01.2021-12-31.clim</path>
      <path>/projectnb/dietzelab/dongchen/All_NEON_SDA/NEON42/ERA5_2012_2021/1000004900/ERA5.7.2012-01-01.2021-12-31.clim</path>
      <path>/projectnb/dietzelab/dongchen/All_NEON_SDA/NEON42/ERA5_2012_2021/1000004900/ERA5.8.2012-01-01.2021-12-31.clim</path>
      <path>/projectnb/dietzelab/dongchen/All_NEON_SDA/NEON42/ERA5_2012_2021/1000004900/ERA5.9.2012-01-01.2021-12-31.clim</path>
     </path>
    </met>
    <pft.site>
     <path>/projectnb/dietzelab/dongchen/All_NEON_SDA/NEON42/site_pft.csv</path>
    </pft.site>
   </inputs>
  </settings.33>
  <settings.34>
   <site>
    <id>1000004934</id>
    <met.start>2012/01/01</met.start>
    <met.end>2021/12/31</met.end>
    <lat>32.95046</lat>
    <lon>-87.39327</lon>
    <name>1000004934</name>
   </site>
   <start.date>2012/01/01</start.date>
   <end.date>2021/12/31</end.date>
   <inputs>
    <met>
     <source>ERA5</source>
     <output>SIPNET</output>
     <id></id>
     <path>
      <path>/projectnb/dietzelab/dongchen/All_NEON_SDA/NEON42/ERA5_2012_2021/1000004934/ERA5.1.2012-01-01.2021-12-31.clim</path>
      <path>/projectnb/dietzelab/dongchen/All_NEON_SDA/NEON42/ERA5_2012_2021/1000004934/ERA5.10.2012-01-01.2021-12-31.clim</path>
      <path>/projectnb/dietzelab/dongchen/All_NEON_SDA/NEON42/ERA5_2012_2021/1000004934/ERA5.2.2012-01-01.2021-12-31.clim</path>
      <path>/projectnb/dietzelab/dongchen/All_NEON_SDA/NEON42/ERA5_2012_2021/1000004934/ERA5.3.2012-01-01.2021-12-31.clim</path>
      <path>/projectnb/dietzelab/dongchen/All_NEON_SDA/NEON42/ERA5_2012_2021/1000004934/ERA5.4.2012-01-01.2021-12-31.clim</path>
      <path>/projectnb/dietzelab/dongchen/All_NEON_SDA/NEON42/ERA5_2012_2021/1000004934/ERA5.5.2012-01-01.2021-12-31.clim</path>
      <path>/projectnb/dietzelab/dongchen/All_NEON_SDA/NEON42/ERA5_2012_2021/1000004934/ERA5.6.2012-01-01.2021-12-31.clim</path>
      <path>/projectnb/dietzelab/dongchen/All_NEON_SDA/NEON42/ERA5_2012_2021/1000004934/ERA5.7.2012-01-01.2021-12-31.clim</path>
      <path>/projectnb/dietzelab/dongchen/All_NEON_SDA/NEON42/ERA5_2012_2021/1000004934/ERA5.8.2012-01-01.2021-12-31.clim</path>
      <path>/projectnb/dietzelab/dongchen/All_NEON_SDA/NEON42/ERA5_2012_2021/1000004934/ERA5.9.2012-01-01.2021-12-31.clim</path>
     </path>
    </met>
    <pft.site>
     <path>/projectnb/dietzelab/dongchen/All_NEON_SDA/NEON42/site_pft.csv</path>
    </pft.site>
   </inputs>
  </settings.34>
  <settings.35>
   <site>
    <id>1000004919</id>
    <met.start>2012/01/01</met.start>
    <met.end>2021/12/31</met.end>
    <lat>31.19484</lat>
    <lon>-84.46861</lon>
    <name>1000004919</name>
   </site>
   <start.date>2012/01/01</start.date>
   <end.date>2021/12/31</end.date>
   <inputs>
    <met>
     <source>ERA5</source>
     <output>SIPNET</output>
     <id></id>
     <path>
      <path>/projectnb/dietzelab/dongchen/All_NEON_SDA/NEON42/ERA5_2012_2021/1000004919/ERA5.1.2012-01-01.2021-12-31.clim</path>
      <path>/projectnb/dietzelab/dongchen/All_NEON_SDA/NEON42/ERA5_2012_2021/1000004919/ERA5.10.2012-01-01.2021-12-31.clim</path>
      <path>/projectnb/dietzelab/dongchen/All_NEON_SDA/NEON42/ERA5_2012_2021/1000004919/ERA5.2.2012-01-01.2021-12-31.clim</path>
      <path>/projectnb/dietzelab/dongchen/All_NEON_SDA/NEON42/ERA5_2012_2021/1000004919/ERA5.3.2012-01-01.2021-12-31.clim</path>
      <path>/projectnb/dietzelab/dongchen/All_NEON_SDA/NEON42/ERA5_2012_2021/1000004919/ERA5.4.2012-01-01.2021-12-31.clim</path>
      <path>/projectnb/dietzelab/dongchen/All_NEON_SDA/NEON42/ERA5_2012_2021/1000004919/ERA5.5.2012-01-01.2021-12-31.clim</path>
      <path>/projectnb/dietzelab/dongchen/All_NEON_SDA/NEON42/ERA5_2012_2021/1000004919/ERA5.6.2012-01-01.2021-12-31.clim</path>
      <path>/projectnb/dietzelab/dongchen/All_NEON_SDA/NEON42/ERA5_2012_2021/1000004919/ERA5.7.2012-01-01.2021-12-31.clim</path>
      <path>/projectnb/dietzelab/dongchen/All_NEON_SDA/NEON42/ERA5_2012_2021/1000004919/ERA5.8.2012-01-01.2021-12-31.clim</path>
      <path>/projectnb/dietzelab/dongchen/All_NEON_SDA/NEON42/ERA5_2012_2021/1000004919/ERA5.9.2012-01-01.2021-12-31.clim</path>
     </path>
    </met>
    <pft.site>
     <path>/projectnb/dietzelab/dongchen/All_NEON_SDA/NEON42/site_pft.csv</path>
    </pft.site>
   </inputs>
  </settings.35>
  <settings.36>
   <site>
    <id>1000004945</id>
    <met.start>2012/01/01</met.start>
    <met.end>2021/12/31</met.end>
    <lat>42.5369</lat>
    <lon>-72.17266</lon>
    <name>1000004945</name>
   </site>
   <start.date>2012/01/01</start.date>
   <end.date>2021/12/31</end.date>
   <inputs>
    <met>
     <source>ERA5</source>
     <output>SIPNET</output>
     <id></id>
     <path>
      <path>/projectnb/dietzelab/dongchen/All_NEON_SDA/NEON42/ERA5_2012_2021/1000004945/ERA5.1.2012-01-01.2021-12-31.clim</path>
      <path>/projectnb/dietzelab/dongchen/All_NEON_SDA/NEON42/ERA5_2012_2021/1000004945/ERA5.10.2012-01-01.2021-12-31.clim</path>
      <path>/projectnb/dietzelab/dongchen/All_NEON_SDA/NEON42/ERA5_2012_2021/1000004945/ERA5.2.2012-01-01.2021-12-31.clim</path>
      <path>/projectnb/dietzelab/dongchen/All_NEON_SDA/NEON42/ERA5_2012_2021/1000004945/ERA5.3.2012-01-01.2021-12-31.clim</path>
      <path>/projectnb/dietzelab/dongchen/All_NEON_SDA/NEON42/ERA5_2012_2021/1000004945/ERA5.4.2012-01-01.2021-12-31.clim</path>
      <path>/projectnb/dietzelab/dongchen/All_NEON_SDA/NEON42/ERA5_2012_2021/1000004945/ERA5.5.2012-01-01.2021-12-31.clim</path>
      <path>/projectnb/dietzelab/dongchen/All_NEON_SDA/NEON42/ERA5_2012_2021/1000004945/ERA5.6.2012-01-01.2021-12-31.clim</path>
      <path>/projectnb/dietzelab/dongchen/All_NEON_SDA/NEON42/ERA5_2012_2021/1000004945/ERA5.7.2012-01-01.2021-12-31.clim</path>
      <path>/projectnb/dietzelab/dongchen/All_NEON_SDA/NEON42/ERA5_2012_2021/1000004945/ERA5.8.2012-01-01.2021-12-31.clim</path>
      <path>/projectnb/dietzelab/dongchen/All_NEON_SDA/NEON42/ERA5_2012_2021/1000004945/ERA5.9.2012-01-01.2021-12-31.clim</path>
     </path>
    </met>
    <pft.site>
     <path>/projectnb/dietzelab/dongchen/All_NEON_SDA/NEON42/site_pft.csv</path>
    </pft.site>
   </inputs>
  </settings.36>
  <settings.37>
   <site>
    <id>1000004901</id>
    <met.start>2012/01/01</met.start>
    <met.end>2021/12/31</met.end>
    <lat>37.10878</lat>
    <lon>-119.73228</lon>
    <name>1000004901</name>
   </site>
   <start.date>2012/01/01</start.date>
   <end.date>2021/12/31</end.date>
   <inputs>
    <met>
     <source>ERA5</source>
     <output>SIPNET</output>
     <id></id>
     <path>
      <path>/projectnb/dietzelab/dongchen/All_NEON_SDA/NEON42/ERA5_2012_2021/1000004901/ERA5.1.2012-01-01.2021-12-31.clim</path>
      <path>/projectnb/dietzelab/dongchen/All_NEON_SDA/NEON42/ERA5_2012_2021/1000004901/ERA5.10.2012-01-01.2021-12-31.clim</path>
      <path>/projectnb/dietzelab/dongchen/All_NEON_SDA/NEON42/ERA5_2012_2021/1000004901/ERA5.2.2012-01-01.2021-12-31.clim</path>
      <path>/projectnb/dietzelab/dongchen/All_NEON_SDA/NEON42/ERA5_2012_2021/1000004901/ERA5.3.2012-01-01.2021-12-31.clim</path>
      <path>/projectnb/dietzelab/dongchen/All_NEON_SDA/NEON42/ERA5_2012_2021/1000004901/ERA5.4.2012-01-01.2021-12-31.clim</path>
      <path>/projectnb/dietzelab/dongchen/All_NEON_SDA/NEON42/ERA5_2012_2021/1000004901/ERA5.5.2012-01-01.2021-12-31.clim</path>
      <path>/projectnb/dietzelab/dongchen/All_NEON_SDA/NEON42/ERA5_2012_2021/1000004901/ERA5.6.2012-01-01.2021-12-31.clim</path>
      <path>/projectnb/dietzelab/dongchen/All_NEON_SDA/NEON42/ERA5_2012_2021/1000004901/ERA5.7.2012-01-01.2021-12-31.clim</path>
      <path>/projectnb/dietzelab/dongchen/All_NEON_SDA/NEON42/ERA5_2012_2021/1000004901/ERA5.8.2012-01-01.2021-12-31.clim</path>
      <path>/projectnb/dietzelab/dongchen/All_NEON_SDA/NEON42/ERA5_2012_2021/1000004901/ERA5.9.2012-01-01.2021-12-31.clim</path>
     </path>
    </met>
    <pft.site>
     <path>/projectnb/dietzelab/dongchen/All_NEON_SDA/NEON42/site_pft.csv</path>
    </pft.site>
   </inputs>
  </settings.37>
  <settings.38>
   <site>
    <id>1000004918</id>
    <met.start>2012/01/01</met.start>
    <met.end>2021/12/31</met.end>
    <lat>28.12504</lat>
    <lon>-81.4362</lon>
    <name>1000004918</name>
   </site>
   <start.date>2012/01/01</start.date>
   <end.date>2021/12/31</end.date>
   <inputs>
    <met>
     <source>ERA5</source>
     <output>SIPNET</output>
     <id></id>
     <path>
      <path>/projectnb/dietzelab/dongchen/All_NEON_SDA/NEON42/ERA5_2012_2021/1000004918/ERA5.1.2012-01-01.2021-12-31.clim</path>
      <path>/projectnb/dietzelab/dongchen/All_NEON_SDA/NEON42/ERA5_2012_2021/1000004918/ERA5.10.2012-01-01.2021-12-31.clim</path>
      <path>/projectnb/dietzelab/dongchen/All_NEON_SDA/NEON42/ERA5_2012_2021/1000004918/ERA5.2.2012-01-01.2021-12-31.clim</path>
      <path>/projectnb/dietzelab/dongchen/All_NEON_SDA/NEON42/ERA5_2012_2021/1000004918/ERA5.3.2012-01-01.2021-12-31.clim</path>
      <path>/projectnb/dietzelab/dongchen/All_NEON_SDA/NEON42/ERA5_2012_2021/1000004918/ERA5.4.2012-01-01.2021-12-31.clim</path>
      <path>/projectnb/dietzelab/dongchen/All_NEON_SDA/NEON42/ERA5_2012_2021/1000004918/ERA5.5.2012-01-01.2021-12-31.clim</path>
      <path>/projectnb/dietzelab/dongchen/All_NEON_SDA/NEON42/ERA5_2012_2021/1000004918/ERA5.6.2012-01-01.2021-12-31.clim</path>
      <path>/projectnb/dietzelab/dongchen/All_NEON_SDA/NEON42/ERA5_2012_2021/1000004918/ERA5.7.2012-01-01.2021-12-31.clim</path>
      <path>/projectnb/dietzelab/dongchen/All_NEON_SDA/NEON42/ERA5_2012_2021/1000004918/ERA5.8.2012-01-01.2021-12-31.clim</path>
      <path>/projectnb/dietzelab/dongchen/All_NEON_SDA/NEON42/ERA5_2012_2021/1000004918/ERA5.9.2012-01-01.2021-12-31.clim</path>
     </path>
    </met>
    <pft.site>
     <path>/projectnb/dietzelab/dongchen/All_NEON_SDA/NEON42/site_pft.csv</path>
    </pft.site>
   </inputs>
  </settings.38>
  <settings.39>
   <site>
    <id>1000004924</id>
    <met.start>2012/01/01</met.start>
    <met.end>2021/12/31</met.end>
    <lat>44.06388</lat>
    <lon>-71.28731</lon>
    <name>1000004924</name>
   </site>
   <start.date>2012/01/01</start.date>
   <end.date>2021/12/31</end.date>
   <inputs>
    <met>
     <source>ERA5</source>
     <output>SIPNET</output>
     <id></id>
     <path>
      <path>/projectnb/dietzelab/dongchen/All_NEON_SDA/NEON42/ERA5_2012_2021/1000004924/ERA5.1.2012-01-01.2021-12-31.clim</path>
      <path>/projectnb/dietzelab/dongchen/All_NEON_SDA/NEON42/ERA5_2012_2021/1000004924/ERA5.10.2012-01-01.2021-12-31.clim</path>
      <path>/projectnb/dietzelab/dongchen/All_NEON_SDA/NEON42/ERA5_2012_2021/1000004924/ERA5.2.2012-01-01.2021-12-31.clim</path>
      <path>/projectnb/dietzelab/dongchen/All_NEON_SDA/NEON42/ERA5_2012_2021/1000004924/ERA5.3.2012-01-01.2021-12-31.clim</path>
      <path>/projectnb/dietzelab/dongchen/All_NEON_SDA/NEON42/ERA5_2012_2021/1000004924/ERA5.4.2012-01-01.2021-12-31.clim</path>
      <path>/projectnb/dietzelab/dongchen/All_NEON_SDA/NEON42/ERA5_2012_2021/1000004924/ERA5.5.2012-01-01.2021-12-31.clim</path>
      <path>/projectnb/dietzelab/dongchen/All_NEON_SDA/NEON42/ERA5_2012_2021/1000004924/ERA5.6.2012-01-01.2021-12-31.clim</path>
      <path>/projectnb/dietzelab/dongchen/All_NEON_SDA/NEON42/ERA5_2012_2021/1000004924/ERA5.7.2012-01-01.2021-12-31.clim</path>
      <path>/projectnb/dietzelab/dongchen/All_NEON_SDA/NEON42/ERA5_2012_2021/1000004924/ERA5.8.2012-01-01.2021-12-31.clim</path>
      <path>/projectnb/dietzelab/dongchen/All_NEON_SDA/NEON42/ERA5_2012_2021/1000004924/ERA5.9.2012-01-01.2021-12-31.clim</path>
     </path>
    </met>
    <pft.site>
     <path>/projectnb/dietzelab/dongchen/All_NEON_SDA/NEON42/site_pft.csv</path>
    </pft.site>
   </inputs>
  </settings.39>
 </run>
 <multisettings>
  <multisettings>run</multisettings>
 </multisettings>
</pecan>
