<?xml version="1.0"?>
  <pecan>
  <state.data.assimilation>
  <process.variance>FALSE</process.variance>
  <sample.parameters>TRUE</sample.parameters>
  <adjustment>TRUE</adjustment>
  <data>
  <format_id>1000000040</format_id>
  <input.id>1000013298</input.id>
  </data>
  <inputs>
  <file>
  <input.id>1000013298</input.id>
  <operator>direct</operator>
  <min_value>0</min_value>
  <max_value>9999</max_value>
  <variable.name>
  <variable.name>AbvGrndWood</variable.name>
  </variable.name>
  </file>
  <file>
  <input.id>1000013298</input.id>
  <operator>direct</operator>
  <min_value>-9999</min_value>
  <max_value>9999</max_value>
  <variable.name>
  <variable.name>NEE</variable.name>
  </variable.name>
  </file>
  <file>
  <input.id>1000013298</input.id>
  <operator>direct</operator>
  <min_value>0</min_value>
  <max_value>9999</max_value>
  <variable.name>
  <variable.name>Qle</variable.name>
  </variable.name>
  </file>
  <file>
  <input.id>1000013298</input.id>
  <operator>direct</operator>
  <min_value>0</min_value>
  <max_value>9999</max_value>
  <variable.name>
  <variable.name>LAI</variable.name>
  </variable.name>
  </file>
  <file>
  <input.id>1000013298</input.id>
  <operator>direct</operator>
  <min_value>0</min_value>
  <max_value>9999</max_value>
  <variable.name>
  <variable.name>TotSoilCarb</variable.name>
  </variable.name>
  </file>
  <file>
  <input.id>1000013298</input.id>
  <operator>direct</operator>
  <min_value>0</min_value>
  <max_value>1</max_value>
  <variable.name>
  <variable.name>SoilMoistFrac</variable.name>
  </variable.name>
  </file>
  <file>
  <input.id>1000013298</input.id>
  <operator>direct</operator>
  <min_value>0</min_value>
  <max_value>9999</max_value>
  <variable.name>
  <variable.name>litter_carbon_content</variable.name>
  </variable.name>
  </file>
  </inputs>
  <state.variables>
  <variable>
  <variable.name>AbvGrndWood</variable.name>
  <min_value>0</min_value>
  <max_value>9999</max_value>
  </variable>
  <variable>
  <variable.name>NEE</variable.name>
  <unit>umol C m-2 s-1</unit>
  <min_value>-9999</min_value>
  <max_value>9999</max_value>
  </variable>
  <variable>
  <variable.name>Qle</variable.name>
  <min_value>0</min_value>
  <max_value>9999</max_value>
  </variable>
  <variable>
  <variable.name>LAI</variable.name>
  <min_value>0</min_value>
  <max_value>9999</max_value>
  </variable>
  <variable>
  <variable.name>TotSoilCarb</variable.name>
  <min_value>0</min_value>
  <max_value>9999</max_value>
  </variable>
  <variable>
  <variable.name>SoilMoistFrac</variable.name>
  <min_value>0</min_value>
  <max_value>1</max_value>
  </variable>
  <variable>
  <variable.name>litter_carbon_content</variable.name>
  <min_value>0</min_value>
  <max_value>9999</max_value>
  </variable>
  </state.variables>
  <forecast.time.step>day</forecast.time.step>
  <start.date>2017-01-01</start.date>
  <end.date>2018-11-05</end.date>
  <n.ensemble>1</n.ensemble>
  </state.data.assimilation>
  <info>
  <notes>LE fix</notes>
  <userid>-1</userid>
  <username></username>
  <date>2019/01/04 10:19:35 +0000</date>
  </info>
  <database>
  <bety>
  <user>bety</user>
  <password>bety</password>
  <host>psql-pecan.bu.edu</host>
  <dbname>bety</dbname>
  <driver>PostgreSQL</driver>
  <write>TRUE</write>
  </bety>
  <dbfiles>/projectnb/dietzelab/pecan.data/dbfiles/</dbfiles>
  </database>
  <pfts>
  <pft>
  <name>temperate.deciduous.ALL</name>
  <constants>
  <num>1</num>
  </constants>
  <posteriorid>1000012409</posteriorid>
  </pft>
  </pfts>
  <meta.analysis>
  <iter>3000</iter>
  <random.effects>FALSE</random.effects>
  </meta.analysis>
  <ensemble>
  <size>100</size>
  <variable>NEE</variable>
  <start.year>2020</start.year>
  <end.year>2020</end.year>
  <samplingspace>
  <parameters>
  <method>uniform</method>
  </parameters>
  <met>
  <method>sampling</method>
  </met>
  <poolinitcond>
  <method>sampling</method>
  </poolinitcond>
  </samplingspace>
  </ensemble>
  <model>
  <default.param>/fs/data3/kzarada/US_WCr/data/WillowCreek.param</default.param>
  <id>1000000030</id>
  </model>
  <run>
  <site>
  <id>676</id>
  <met.start>2018-08-26</met.start>
  <met.end>2018-09-23</met.end>
  </site>
  <inputs>
  <poolinitcond>
  <source>BADM</source>
  </poolinitcond>
  <met>
  <source>NOAA_GEFS</source>
  <output>SIPNET</output>
  </met>
  </inputs>
  <start.date>2018-12-05</start.date>
  <end.date>2018-12-20</end.date>
  </run>
  <host>
  <name>localhost</name>
  </host>
  </pecan>